Workbook

Sheet S1 - Interventions
A1: Supplementary File S1. Extracted data from interventions years 2000-2025
A2: Notes: Papers are grouped by the review which they were mentioned in. If a paper was mentioned in more than one review it has only been included once.
A3: Papers in these subsection were then grouped based on efficacy; Column E: "Effective", "Not effective" and "All groups improved".
A4: Where interventions led to comparable improvements in both the intervention and control groups, they were coded as "All groups improved".
A5: For age, reasonable assumptions/calculations were made to impute missing additional data for higher-powered downstream analyses (see individual cells for exact calculations; where there is no calculation, the mean was provided in the paper).
A6: In terms of behaviour change techniques (BCTs) (column 'AC'), all interventions used the domain ‘BCIO:007017: monitoring’ as in 'BCIO:007026: provide biofeedback', so this was not specified in the datasheet. Where monitoring was specified, it was an additional monitoring BCT (i.e self-monitoring results through an app).
A7: BCTs for Celis-Morales et al. 2017; Livingstone et al. 2016 and Damschroder et al. 2020 were coded from their respective protocol papers, published separately (DOIs: 10.1007/s12263-014-0450-2 and 10.2196/12526).
A9: Authors | B9: Title | C9: Year | D9: DOI | E9: Effective? | F9: Behaviour | G9: Number of target behaviours | H9: Grouped biofeedback markers | I9: Biofeedback markers | J9: Specific biofeedback markers | K9: Number of biofeedback markers | L9: Study design | M9: Population | N9: Number of participants | O9: Proportion female | P9: Mean age | Q9: Income identified? | R9: Education identified? | S9: Intervention period | T9: Intervention design | U9: Education/counselling | V9: Measured outcome(s) | W9: BC primary outcome? | X9: Reported results | Y9: Measured post-intervention maintenance? | Z9: Communication mode | AA9: Number of modes of communication | AB9: Frequency of feedback | AC9: Behaviour Change Theory | AD9: Behaviour Change Techniques [DOMAIN LEVEL] | AE9: Number of BCTs used | AF9: BCT for monitoring specifically (non-biomarker)?
A10: Papers from Richardson et al., 2023 DOI:10.2196/44359
A11: Babazono, A., Kame, C., Ishihara, R., Yamamoto, E., Hillman, A. L. | B11: Patient-motivated prevention of lifestyle-related disease in Japan: a randomized, controlled clinical trial | C11: 2007 | D11: 10.2165/00115677-200715020-00007 | E11: Effective | F11: Alcohol reduction, Diet, Physical activity | G11: 3 | H11: {=_xlfn.TEXTJOIN(", ", TRUE, IF(OR(ISNUMBER(SEARCH({"blood pressure","heart rate","anthropometrics","ecg","vo2max","spirometry","respiratory rate"},I11))),"Physiological", ""), IF(OR(ISNUMBER(SEARCH({"genetic"},I11))),"Risk", ""), IF(OR(ISNUMBER(SEARCH({"ultrasound","uv photog","facial","oral","CT scan"},I11))),"Imaging", ""), IF(OR(ISNUMBER(SEARCH({"glucose","hb1ac","lipids","nutrient"},I11))),"Blood", ""),IF(OR(ISNUMBER(SEARCH({"anthropometrics"},I11))),"Anthropometry", ""))} -> Physiological, Blood, Anthropometry | I11: Blood pressure, HbA1c, lipids, anthropometrics | J11: Blood pressure, HbA1c, lipids, weight/BMI | K11: 4 | L11: Randomised intervention | M11: General practice patients referred by GP for program, study included people with stage 1 hypertension or elevated hbA1c | N11: 87 | O11: 58.6 | P11: 64.4 | Q11: No | R11: No | S11: 12 months | T11: Patients were randomised into either the Health Promotion Program (HPP) or control groups. All patients had biomarker testing at baseline, 4, 6 and 12 months. The intervention group were encouraged to set goals and select their own lifestyle improvements with the support of dietitians, exercise instructors and nurses. Home-visits were made twice per year for follow up and support. The control group received their health results and general printed information about exercise only. | U11: Yes | V11: Primary outcomes included changes in vegetable intake and PA levels (steps per day). Secondary measures included bodyweight, BMI, BP, blood lipids, HbA1c, and a general health questionanaire (GHQ30). | W11: Yes | X11: Intervention group significantly increased their mean steps per day (from 7,345 to 10,373, p.<0.001). Control group did not. The difference in steps between intervention and control was statistically significant. After a year, the proportion of patients consuming ≥2 meals with servings of any type of vegetable per day was 85% (up from 73.9%), and the control group was 73.2% (up from 70.7%). Intervention group participants were more likely to consume ≥2 meals with any type of vegetable than the control group (OR 3.8; 95%CI 1.0-14.0, p<0.05). Consumption of green/yellow vegetables also increased among intervention participants, with 50% (up from 34.8%) consuming ≥2 meals with green/yellow yegetables. This did not change in control group participants. Thus, the intervention group members were more likely to consume ≥2 meals with green/yellow vegetables (OR 4.2, 95%CI 1.4-12.6, p<0.05). There were no statistically significant changes in body weight, BMI, BP, cholesterol, TGs, HbA1c or GHQ30. | Y11: No | Z11: In person | AA11: 1 | AB11: Once | AC11: Health Belief Model, Transtheoretical Model | AD11: Goal directed BCT Social support BCT | AE11: 2
A12: Almeida, V., Littlejohn, P., Cop, I., Brown, E., Afroze, R., Davison, K. M. | B12: Comparison of Nutrigenomics Technology Interface Tools for Consumers and Health Professionals: A Sequential Explanatory Mixed Methods Investigation | C12: 2019 | D12: 10.2196/12580 | E12: Effective | F12: Diet | G12: 1 | H12: {=_xlfn.TEXTJOIN(", ", TRUE, IF(OR(ISNUMBER(SEARCH({"blood pressure","heart rate","anthropometrics","ecg","vo2max","spirometry","respiratory rate"},I12))),"Physiological", ""), IF(OR(ISNUMBER(SEARCH({"genetic"},I12))),"Risk", ""), IF(OR(ISNUMBER(SEARCH({"ultrasound","uv photog","facial","oral","CT scan"},I12))),"Imaging", ""), IF(OR(ISNUMBER(SEARCH({"glucose","hb1ac","lipids","nutrient"},I12))),"Blood", ""),IF(OR(ISNUMBER(SEARCH({"anthropometrics"},I12))),"Anthropometry", ""))} -> Risk | I12: Genetics | J12: Genetics | K12: 1 | L12: RCT | M12: Adults aged 37-57 years (mean age 45.8 years, SD 5.8). | N12: 55 | O12: 74.6 | P12: 45.8 | Q12: Yes | R12: Yes | S12: 9 weeks | T12: Participants were randomised to receive a standard nutrition-based gene test report (control; n=19) or a practitioner-facilitated personalised nutrition intervention (intervention; n=36). | U12: Yes | V12: Primary: Differences in the diet quality score (Healthy Eating Index–Canadian [HEI-C]; proportion [%] of calories from total fat, saturated fat, and sugar; omega 3 fatty acid intake [grams]; sodium intake [milligrams]); as well as health-related quality of life (HRQoL) scale score. Secondary: Anthropometrics, self-efficacy. | W12: Yes | X12: Percentage of calories from total fat (mean difference [MD]=−5.1%; Wilks’ lambda [λ]=0.817; F1,53= 11.68; P=.001; eta-squared [η²]=0.183 ) as well as from saturated fat (MD=−1.7%; λ=0.816; F1,53=11.71; P=.001; η²=0.18) and health-related quality of life (HRQoL) scores (MD=8.1 points; λ=0.914; F1,53=4.92; P=.03; η²=0.086). There were significant differences between groups over time for sodium (λ=0.846; F1,53=9.47; P=.003; η²=0.15) and HEI-C scores (λ=0.660; F1,53=27.43; P<.001; η²=0.35. | Y12: No | Z12: In person | AA12: 1 | AB12: Once | AC12: Transtheoretical Model | AD12: Goal directed BCT | AE12: 1
A13: Celis-Morales, C., Livingstone, K. M., Marsaux, C. F., Macready, A. L., Fallaize, R., O'Donovan, C. B., Woolhead, C., Forster, H., Walsh, M. C., Navas-Carretero, S., San-Cristobal, R., Tsirigoti, L., Lambrinou, C. P., Mavrogianni, C., Moschonis, G., Kolossa, S., Hallmann, J., Godlewska, M., Surwillo, A., Traczyk, I., Drevon, C. A., Bouwman, J., van Ommen, B., Grimaldi, K., Parnell, L. D., Matthews, J. N., Manios, Y., Daniel, H., Martinez, J. A., Lovegrove, J. A., Gibney, E. R., Brennan, L., Saris, W. H., Gibney, M., Mathers, J. C., Food4Me, Study | B13: Effect of personalized nutrition on health-related behaviour change: evidence from the Food4Me European randomized controlled trial | C13: 2017 | D13: 10.1093/ije/dyw186 | E13: Effective | F13: Diet | G13: 1 | H13: {=_xlfn.TEXTJOIN(", ", TRUE, IF(OR(ISNUMBER(SEARCH({"blood pressure","heart rate","anthropometrics","ecg","vo2max","spirometry","respiratory rate"},I13))),"Physiological", ""), IF(OR(ISNUMBER(SEARCH({"genetic"},I13))),"Risk", ""), IF(OR(ISNUMBER(SEARCH({"ultrasound","uv photog","facial","oral","CT scan"},I13))),"Imaging", ""), IF(OR(ISNUMBER(SEARCH({"glucose","hb1ac","lipids","nutrient"},I13))),"Blood", ""),IF(OR(ISNUMBER(SEARCH({"anthropometrics"},I13))),"Anthropometry", ""))} -> Physiological, Risk, Blood, Anthropometry | I13: Genetics, glucose, lipids, nutrient biomarkers, anthropometrics | J13: Genetics, weight/BMI, blood glucose, total cholesterol, carotenoids, omega-3 fatty acid index and 32 other fatty acids, and vitamin D | K13: 5 | L13: RCT | M13: Adults. | N13: 1488 | O13: 59 | P13: 39.8 | Q13: No | R13: No | S13: 6 months | T13: Four-arm intervention: Control group/Level 0 (L0): non-personalised dietary, body weight and physical activity (PA) advice based on population guidelines; Level 1 (L1): personalised nutrition (PN) advice based on individual dietary intake data alone; Level 2 (L2): PN advice based on individual dietary intake and phenotypic data; Level 3 (L3): PN advice based on individual dietary intake and phenotypic and genotypic data. | U13: No | V13: Primary: Changes to dietary intake. Secondary: anthropometric measures (body weight (BW), body mass index (BMI) and waist circumference) and blood biomarkers (total cholesterol (TC), carotenoids and fatty acids). | W13: Yes | X13: All participants improved their diet over the intervention period. Individuals receiving PN advice consumed less red meat (8.5%), salt (6.3%), and energy (4.4%), and had higher healthy eating index (HEI) scores (2.6%) compared with the Control group. No significant differences were seen in the other food groups. Changes in dietary outcomes did not differ between Levels 1, 2 and 3 of PN. Nutrient changes were assessed in salt, saturated fat, dietary fibre, folate and polyunsaturated fatty acids (PUFAs). Participants receiving PN advice consumed less salt (8.9%) and saturated fat (7.8%) and had higher folate intake (11.5%) compared with controls. No significant changes to biomarkers or anthropometric measures at conclusion of the intervention. | Y13: No | Z13: Written Communication | AA13: 1 | AB13: Once | AC13: None | AD13: Monitoring BCT Increase awareness of consequences BCT Social Support | AE13: 3 | AF13: BCIO:007019: record behaviour without feedback BCT **NOTE: from BCTO hierarchy sheet The monitoring agent can be a human or a technical device. If recording is part of a data collection procedure rather than a strategy aimed at changing behaviour, do not code; if feedback given, code only 'provide feedback on outcome of behaviour BCT' and not this class; if observing behaviour code 'observe behaviour without feedback BCT'.
A14: Nielsen, D. E., El-Sohemy, A. | B14: Disclosure of genetic information and change in dietary intake: a randomized controlled trial | C14: 2014 | D14: 10.1371/journal.pone.0112665 | E14: Effective | F14: Diet | G14: 1 | H14: {=_xlfn.TEXTJOIN(", ", TRUE, IF(OR(ISNUMBER(SEARCH({"blood pressure","heart rate","anthropometrics","ecg","vo2max","spirometry","respiratory rate"},I14))),"Physiological", ""), IF(OR(ISNUMBER(SEARCH({"genetic"},I14))),"Risk", ""), IF(OR(ISNUMBER(SEARCH({"ultrasound","uv photog","facial","oral","CT scan"},I14))),"Imaging", ""), IF(OR(ISNUMBER(SEARCH({"glucose","hb1ac","lipids","nutrient"},I14))),"Blood", ""),IF(OR(ISNUMBER(SEARCH({"anthropometrics"},I14))),"Anthropometry", ""))} -> Risk | I14: Genetics | J14: SNPs that affect caffeine metabolism (CYP1A2), vitamin C utilisation (GSTT1 and GSTM1), sweet taste perception (TAS1R2), and sodium-sensitivity (ACE) | K14: 1 | L14: double-blinded, parallel group RCT | M14: Healthy adults (age 26.5+/-3.0 years) | N14: 138 | O14: 78 | P14: 26.5 | Q14: No | R14: Yes | S14: 12 months | T14: Intended to mimic the nature of a direct to-consumer genetic test: all study materials were distributed and completed via mail/electronically. No in-person contact was made with subjects. Subjects who had previously participated in a nutrigenomics research study and had provided a blood sample were invited to complete a 196-item, semi-quantitative Toronto modified Willet food frequency questionnaire (FFQ) and were then randomized to an intervention or control group (2:1 ratio). The intervention group consisted of those who would have either the ‘‘risk’’ or ‘‘non-risk’’ genotype for each of the genes. The dietary report for subjects in the intervention group informed subjects of their genotypes and included a corresponding DNA-based dietary recommendation for daily intake of caffeine, vitamin C, added sugars and sodium. Those who possessed the genotype that has been associated with increased risk of a health outcome when consuming above or below a certain daily amount were given a ‘‘targeted’’ dietary recommendation. For caffeine and sodium, this recommendation was more stringent than the current general recommendation for daily intake, based on previous research that evaluated health outcomes according to genotype at different levels of intake. For added sugars and vitamin C, subjects were to meet the current general recommendation for daily intake, since no previous study has examined how individuals respond to consuming various levels of these nutrients according to genotype. Subjects who possessed the genotype that has not been associated with increased risk received the current general recommendation for daily intake. The control group was e-mailed a report of current general recommendations for the same nutrients without genetic information. Subjects were e-mailed a monthly reminder of their dietary report and additional FFQs were collected at 3- and 12-month follow-up assessments. | U14: No | V14: Primary outcome: change in dietary intakes of caffeine, vitamin C, added sugars, and sodium between the control and intervention groups from baseline to the follow-up assessments. Changes in dietary intakes between baseline and 3-months determined short-term effects of the intervention, while changes in intakes between baseline and 12- months were considered long-term effects. Secondary outcome: the proportion of participants who met recommendations for intake before/after the intervention for dietary components that significantly changed between the control and intervention groups. | W14: Yes | X14: No significant changes from baseline for intakes of caffeine, vitamin C, added sugars, or sodium at the 3-month follow-up among subjects in the intervention risk group, nor among subjects in the intervention non-risk group (Compared to the control group). At 12-month follow-up, intervention risk group subjects who possessed the risk version of the ACE gene (thus given the targeted advice to consume below the Adequate Intake [AI] of 1500 mg/day of sodium), significantly reduced their mean sodium intake (mg/day) from baseline when compared to the control group (-287.3 ±114.1 vs. 129.8 ±118.2, p = 0.008) (control group was given the general recommendation for sodium intake [Tolerable Upper Intake Level (UL): ≤2300 mg/day]). The mean change in sodium intake (mg/day) among non-risk intervention subjects for the the ACE gene (advised to follow the general recommendation for sodium intake), did not differ from the change in intake of the control group at 12-months. Among those in the risk intervention group for the ACE gene, 19% met the targeted recommendation of ≤1500 mg/day at baseline compared to 34% after 12 months (p = 0.06), and 59% met the general recommendation of ≤2300 mg/day at baseline compared to 66% after 12 months (p = 0.41). The mean changes in intakes from baseline for caffeine, vitamin C and added sugars did not differ from the control group at the 12-month follow-up among either the intervention-risk or intervention non-risk group. | Y14: No | Z14: Written Communication | AA14: 1 | AB14: Once | AC14: None | AD14: Increase awareness of consequences BCT Guide to how to perform behaviour BCT | AE14: 2
A15: Williams, D. R., Lewis, N. M. | B15: Effectiveness of nutrition counseling in young adult males | C15: 2002 | D15: 10.1016/S0271-5317(02)00399-8 | E15: Effective | F15: Diet | G15: 1 | H15: {=_xlfn.TEXTJOIN(", ", TRUE, IF(OR(ISNUMBER(SEARCH({"blood pressure","heart rate","anthropometrics","ecg","vo2max","spirometry","respiratory rate"},I15))),"Physiological", ""), IF(OR(ISNUMBER(SEARCH({"genetic"},I15))),"Risk", ""), IF(OR(ISNUMBER(SEARCH({"ultrasound","uv photog","facial","oral","CT scan"},I15))),"Imaging", ""), IF(OR(ISNUMBER(SEARCH({"glucose","hb1ac","lipids","nutrient"},I15))),"Blood", ""),IF(OR(ISNUMBER(SEARCH({"anthropometrics"},I15))),"Anthropometry", ""))} -> Blood | I15: Lipids | J15: Cholesterol | K15: 1 | L15: Randomised trial | M15: Healthy males (aged 21.5 +/- 1.4 years) | N15: 45 | O15: 0 | P15: 21.5 | Q15: No | R15: No | S15: 6 weeks | T15: Men were randomly assigned to one of four groups; nutrition counselling and measurement of serum cholesterol (NC + SC), nutrition counselling only (NC), measurement of serum cholesterol only (SC), or control (C). At weeks 1 and 6, participants completed a 24-hour recall, a 2-day food record, and a food frequency questionnaire. The groups who recieved nutrition counselling were presented with a computer nutrient analysis of their food intake to help them identify sources of fat in their diet. | U15: Yes | V15: Dietary changes, fat intake (% of E), perception of nutrition counselling | W15: Yes | X15: In the NC + SC group there was a significant reduction in fat (-3.2 ±1.4, P 0.02) from pre- to post-intervention, the NC, SC and C groups did not experience a significant change in percent calories from fat. Participants who received nutrition counseling (NC + SC and NC groups) increased their servings of fresh fruit, “light” salad dressing, and <30% fat ground beef after the counseling (P 0.05). There were no differences in the food frequency from pre- to post-assessment in the SC and C groups. All of the men who received nutrition counselling reported gaining some nutrition knowledge by their participation in this study and 92% said that the nutrition counselling convinced them that lowering their dietary fat intake would reduce their risk of CHD. 96% of the participants stated they had made dietary changes as a result of the study, such as "eating less fast food" and "eating more fruits and vegetables". A small subgroup (31%) of the participants responded negatively to goal setting. 92% said seeing a model of the “clogged artery” in a nutrition counselling session was helpful. | Y15: No | Z15: In person | AA15: 1 | AB15: Once | AC15: None | AD15: Goal directed BCT Increase awareness of consequences BCT | AE15: 2
A16: Livingstone, K. M., Celis-Morales, C., Navas-Carretero, S., San-Cristobal, R., Macready, A. L., Fallaize, R., Forster, H., Woolhead, C., O'Donovan, C. B., Marsaux, C. F., Kolossa, S., Tsirigoti, L., Lambrinou, C. P., Moschonis, G., Godlewska, M., Surwillo, A., Drevon, C. A., Manios, Y., Traczyk, I., Gibney, E. R., Brennan, L., Walsh, M. C., Lovegrove, J. A., Saris, W. H., Daniel, H., Gibney, M., Martinez, J. A., Mathers, J. C., Food4Me, Study | B16: Effect of an Internet-based, personalized nutrition randomized trial on dietary changes associated with the Mediterranean diet: the Food4Me Study | C16: 2016 | D16: 10.3945/ajcn.115.129049 | E16: Effective | F16: Diet, Physical activity | G16: 2 | H16: {=_xlfn.TEXTJOIN(", ", TRUE, IF(OR(ISNUMBER(SEARCH({"blood pressure","heart rate","anthropometrics","ecg","vo2max","spirometry","respiratory rate"},I16))),"Physiological", ""), IF(OR(ISNUMBER(SEARCH({"genetic"},I16))),"Risk", ""), IF(OR(ISNUMBER(SEARCH({"ultrasound","uv photog","facial","oral","CT scan"},I16))),"Imaging", ""), IF(OR(ISNUMBER(SEARCH({"glucose","hb1ac","lipids","nutrient"},I16))),"Blood", ""),IF(OR(ISNUMBER(SEARCH({"anthropometrics"},I16))),"Anthropometry", ""))} -> Physiological, Risk, Blood, Anthropometry | I16: Genetics, lipids, nutrient biomarkers, anthropometrics | J16: Genetics, glucose, lipids, nutrient biomarkers, weight/BMI | K16: 4 | L16: RCT | M16: Adults (aged 39.9 ± 13.0 years). | N16: 1270 | O16: 59 | P16: 39.9 | Q16: Unclear | R16: Unclear | S16: 6 months | T16: 6-month, four-arm intervention. Control group/Level 0 (L0): non-personalised dietary, body weight and physical activity (PA) advice based on population guidelines; Level 1 (L1): personalised nutrition (PN) advice based on individual dietary intake data alone; Level 2 (L2): PN advice based on individual dietary intake and phenotypic data; Level 3 (L3): PN advice based on individual dietary intake and phenotypic and genotypic data. | U16: No | V16: Changes to dietary consumption as measured by MedDiet scores. | W16: Yes | X16: MedDiet scores were greater in individuals randomly assigned to PN (mean L1, L2 and L3) than in controls (L0) (PN compared with control arms: 5.20 ± 0.05 and 5.48 ± 0.07, respectively; P = 0.002). MedDiet scores at month 6 in participants who received PN advice on the basis of current diet alone (L1) were not significantly different from those randomly assigned to L2 and L3 [who received advice on the basis of current diet + phenotype (L2) and diet + phenotype + genotype (L3)]. However, MedDiet scores at month 6 for participants who received PN advice in L3 (diet + phenotype + genotype) were greater than in participants in L2 at month 6 (L3 compared with L2: 5.63 ± 0.10 and 5.38 ± 0.10, respectively; P = 0.029). | Y16: No | Z16: Written Communication | AA16: 1 | AB16: Once | AC16: Protection Motivation Theory | AD16: Social support BCT Monitoring BCT Increase awareness of consequences BCT Goal directed BCT | AE16: 4 | AF16: BCIO:007019: record behaviour without feedback BCT **NOTE: from BCTO hierarchy sheet The monitoring agent can be a human or a technical device. If recording is part of a data collection procedure rather than a strategy aimed at changing behaviour, do not code; if feedback given, code only 'provide feedback on outcome of behaviour BCT' and not this class; if observing behaviour code 'observe behaviour without feedback BCT'.
A17: Olson, R., Thompson, S. V., Elliot, D. L., Hess, J. A., Rhoten, K. L., Parker, K. N., Wright, R. R., Wipfli, B., Bettencourt, K. M., Buckmaster, A., Marino, M. | B17: Safety and Health Support for Home Care Workers: The COMPASS Randomized Controlled Trial | C17: 2016 | D17: 10.2105/AJPH.2016.303327 | E17: Effective | F17: Diet, Physical activity, workplace safety behaviours | G17: 2 | H17: {=_xlfn.TEXTJOIN(", ", TRUE, IF(OR(ISNUMBER(SEARCH({"blood pressure","heart rate","anthropometrics","ecg","vo2max","spirometry","respiratory rate"},I17))),"Physiological", ""), IF(OR(ISNUMBER(SEARCH({"genetic"},I17))),"Risk", ""), IF(OR(ISNUMBER(SEARCH({"ultrasound","uv photog","facial","oral","CT scan"},I17))),"Imaging", ""), IF(OR(ISNUMBER(SEARCH({"glucose","hb1ac","lipids","nutrient"},I17))),"Blood", ""),IF(OR(ISNUMBER(SEARCH({"anthropometrics"},I17))),"Anthropometry", ""))} -> Physiological, Blood, Anthropometry | I17: Blood pressure, glucose, lipids, anthropometrics | J17: Blood pressure, glucose, lipids, weight/BMI | K17: 4 | L17: RCT | M17: Healthcare workers (aged 51.6 years, SD=13.2) | N17: 149 | O17: 89 | P17: 51.6 | Q17: No | R17: No | S17: 12 months | T17: Clusters of healthcare workers were filled with workers who had similar availability and location of residences (total of 16 clusters with a range of 7–12 members totalling n=74 intervention; n=74 usual practice), plus an additional intervention participant did not complete baseline but completed subsequent assessments. Once 2 clusters were filled, one was randomized to intervention and the other to usual practice control. After baseline data collection, all participants received immediate feedback on physical measurements relative to normal or healthy standards and were informed of their random assignment. Control participants received pay and materials (compensation for time) and concluded enrollment. The control participants had access to the usual resources provided by their union/s, therefore, it was possible for control participants to attend monthly paid training that matched or exceeded total paid monthly activities for intervention participants. Intervention participants received a brief intervention orientation and additional materials (workbook, knee pad, step counter) before finishing enrollment. The intervention clusters participated in a researcher-led half-day workshop followed by 12 monthly peer-led meetings that were implemented by using scripted workbooks and supporting materials. Team leader recieved additional instructions and brief facilitator training at the beginning and midway through the program. Monthly meetings involved a WorkLife check-in (i.e., rating or sharing current work and life status), educational lesson, goal setting, healthy meal break, WorkLife support (i.e., structured problem solving), and a reflection. Educational lessons and goals alternated between safety and health or well-being topics. COMPASS workbook 1, which was developed and revised on the basis of a pilot study, was used during the first 6 months. Workbook 2, which was developed and tested with a subgroup of original pilot participants, was used during months 7 through 12. Instead of fully scripted lessons, workbook 2 allowed teams to choose a schedule of readings from a menu of options. Each “reading discussion” option included scripted group and individual goal setting. Intervention participants were provided individual and team “certification” incentives for meeting certain attendance and goal completion criteria. | U17: Yes | V17: Primary outcomes: Community of practice (i.e., people engaged in a common activity who interact regularly for shared learning and improvement). Well-being was measured with the 12-item Short Form Health Survey version 2.0; health behaviours including daily fruit and vegetable consumption (via the National Cancer Institute fruit and vegetable screener), reduced daily consumption of high-fat and high-sugar foods (questions about frequency of consuming sugary drinks, sugary snacks, and fast food, and bringing meals from home) PA scale (5 d/wk with 30 minutes of moderate exercise), and safe behaviors and conditions when working in clients' homes (assessed with questionnaire about frequency of specific actions in the past 6 months). Secondary outcomes: Sleep quality (assessed using a single item from the Pittsburgh Sleep Quality Index), Psychosocial experiences and stress measures. An adapted Nordic questionnaire assessed the degree to which musculoskeletal pain and discomfort interfered with normal tasks, functional impairment with activities of daily living, work related injuries, and lost work time attributable to illness or injury. Physiological measures included blood pressure, blood lipids and glucose,BMI, grip strength, hamstring flexibility (using a Sit and Reach box), and a 6-minute walk test. | W17: Yes | X17: Statistically significant and sustained improvement in experienced community of practice (6-month effect size (d) =0.36; P=.023; 12-month d=0.37; P.024); talking with CEs about improving unsafe conditions (12-month d=0.84; P<.001); correcting slip, trip, or fall hazards (12-month d=0.45; P=.027); using new tools or techniques for moving objects or CEs (6-month d=0.65, P=.009); using new tools or techniques for house cleaning (6-month d=0.51; P=.041; 12-month d=0.64; P=.006); and daily fruit and vegetable servings (12-month d=0.31; P=.038). Interestingly, among intervention participants there was a a significant reduction in meals brought from home relative to controls (12-month d=−0.46; P=.014). Longitudinal between-group contrasts for other secondary outcomes included significant improvements in high-density lipoprotein (6-month d=0.22; P=.045) and grip strength (12-month d=0.29; P=.011), as well as a significant reduction in lost work days because of injury (6-month d=−0.66; P=.01). Remaining secondary outcomes among HCWs were predominantly stable and nonsignificant. According to Cohen’s standards for small (d = 0.20), moderate (d = 0.50), and large (d = 0.80) effect sizes, effects for fruit and vegetable consumption and community of practice and were small to moderate, while effect sizes for safety behaviors ranged from moderate to large. | Y17: No | Z17: In person | AA17: 1 | AB17: Once | AC17: None | AD17: Goal directed BCT Social support BCT Monitoring BCT Advise specific behaviour BCT | AE17: 4 | AF17: BCT2.3 Self-monitoring of behaviour
A18: Greene, J., Sacks, R., Piniewski, B., Kil, D., Hahn, J. S. | B18: The impact of an online social network with wireless monitoring devices on physical activity and weight loss | C18: 2013 | D18: 10.1177/2150131912469546 | E18: Effective | F18: Diet, Physical activity | G18: 2 | H18: {=_xlfn.TEXTJOIN(", ", TRUE, IF(OR(ISNUMBER(SEARCH({"blood pressure","heart rate","anthropometrics","ecg","vo2max","spirometry","respiratory rate"},I18))),"Physiological", ""), IF(OR(ISNUMBER(SEARCH({"genetic"},I18))),"Risk", ""), IF(OR(ISNUMBER(SEARCH({"ultrasound","uv photog","facial","oral","CT scan"},I18))),"Imaging", ""), IF(OR(ISNUMBER(SEARCH({"glucose","hb1ac","lipids","nutrient"},I18))),"Blood", ""),IF(OR(ISNUMBER(SEARCH({"anthropometrics"},I18))),"Anthropometry", ""))} -> Physiological, Anthropometry | I18: Anthropometrics | J18: Weight/BMI | K18: 1 | L18: randomised intervention | M18: Adults (most [60%] 50+ years). Age reported as buckets; midpoints of buckets assumed for definite ranges (e.g., "40-49 years" = 44.5 years), while indefinite ranges (age < 40 and age > 60) are estimated as the next nearest 10 (i.e., 30 and 70) as overall ages are 18-79. | N18: 349 | O18: 78.9 | P18: =(30*21.7+44.5*17.9+54.5*42.8+70*17.6)/100 -> 50.1215 | Q18: No | R18: No | S18: 6 months | T18: Participants were randomly assigned to intervention or control groups. All participants received printed guidelines on diet and exercise during their first study visit. Materials included a sample daily meal plan with recommended serving sizes, a handout about recommended daily levels of exercise, and articles about the benefits of exercise and healthy eating. Intervention participants were provided access to the iWell OSN and were given an accelerometer that allowed them to capture PA/step count for upload to the iWell OSN and a wireless weight scale for uploading weight data. With the iWell OSN, participants could connect (“friend”) others in the network, send individual messages to their friends, make public postings, view their contact’s postings, view their PA/steps, view their weight, and compete against others in the network on step count. The iWell OSN also allowed participants to set health-related goals and to receive motivational messages. | U18: No | V18: Physical activity levels, weight, Blood lipids. | W18: Yes | X18: The intervention group significantly increased weekly leisure walking from 129 to 341 minutes, on average, a 164% increase over the 6-month study period, compared with a 47% increase for the control group. The intervention group had larger (non-significant) increases in 9 other areas of PA compared to the control group. The intervention group also lost more weight over the 6-month study period than did the control group (mean 5.2 vs 1.6 pounds). No significant differences between intervention and control for change in LDL-c and HDL-c levels. The intervention group had a significant reduction in triglycerides at 3 months compared with the control group, but it was not sustained at 6 months. In multivariate regressions, the number of messages sent by participants was positively related to increases in leisure time walking minutes and it was negatively related to weight change. In other words, the more messages a participant sent on the iWell OSN, the more likely they increased the number of minutes walked, and reduced their weight. | Y18: No | Z18: Device/Online | AA18: 1 | AB18: More than once | AC18: None | AD18: Social support BCT Goal directed BCT Guide how to perform behaviour BCT Monitoring BCT | AE18: 4 | AF18: BCT2.3 Self-monitoring of behaviour BCT2.4 Self-monitoring of outcome(s) of behaviour
A19: Schopp, L. H., Clark, M. J., Lamberson, W. R., Uhr, D. J., Minor, M. A. | B19: A randomized controlled trial to evaluate outcomes of a workplace self-management intervention and an intensive monitoring intervention | C19: 2017 | D19: 10.1093/her/cyx042 | E19: Effective | F19: Diet, Physical activity, stress management | G19: 3 | H19: {=_xlfn.TEXTJOIN(", ", TRUE, IF(OR(ISNUMBER(SEARCH({"blood pressure","heart rate","anthropometrics","ecg","vo2max","spirometry","respiratory rate"},I19))),"Physiological", ""), IF(OR(ISNUMBER(SEARCH({"genetic"},I19))),"Risk", ""), IF(OR(ISNUMBER(SEARCH({"ultrasound","uv photog","facial","oral","CT scan"},I19))),"Imaging", ""), IF(OR(ISNUMBER(SEARCH({"glucose","hb1ac","lipids","nutrient"},I19))),"Blood", ""),IF(OR(ISNUMBER(SEARCH({"anthropometrics"},I19))),"Anthropometry", ""))} -> Physiological, Blood, Anthropometry | I19: Blood pressure, glucose, lipids, anthropometrics | J19: Triglycerides, high density lipoprotein (HDL), fasting blood glucose, waist circumference, blood pressure. | K19: 4 | L19: RCT | M19: Adults (92 in the intervention group and 88 in the intensive health monitoring group). | N19: 180 | O19: 90 | P19: =(46.94*92+44.58*88)/(92+88) -> 45.786222 | Q19: Yes | R19: Yes | S19: 12 months | T19: The intervention compared outcomes of two voluntary workplace health management methods: an adapted worksite self-management (WSM) approach and an intensive health monitoring (IM) approach. Participants were randomly assigned to either the WSM group or the IM group. WSM participants met weekly in groups of fewer than 12 members for 50 min to review the previous week’s action plan, develop a weekly goal and write an action plan for that goal. Participants could opt-in for group feedback on their action plans, and plans were modified until the participants noted their confidence level in adhering to the plan as at least an 8 on a 10-point scale. Participants also shared challenges, success stories, and health information. Groups were co-facilitated by a project staff member and a trained lay co-leader. The IM intervention consisted of three pre-scheduled biometric screenings and health surveys at baseline, 3 and 12 months. Both groups received adapted CDC health promotion materials on PA, healthy eating, stress reduction, and other primary prevention materials. A Master’s level registered nurse with a background in health promotion provided one-on-one phone counselling to review participants’ biometric results and discuss health promotion materials. | U19: Yes | V19: Self-efficacy was measured via the new general self-efficacy scale (GSE). Health behaviours were measured using the Revised health lifestyle profile II (HPLP-IIR), which measures self-reported frequency of participating in health behaviors (health responsibility, physical activity, nutrition, spiritual growth, interpersonal relations and stress management). Number of days per week on which they engaged in at least 30 mins of PA (any activity that increases heart rate and makes one get out of breath some of the time). Depression symptoms were measured using the Personal health questionnaire (PHQ–8), which contains 8/9 depressive disorder criteria from the DSM-IV. Biomarkers measured included triglycerides, high density lipoprotein (HDL), fasting blood glucose, waist circumference and blood pressure. | W19: Yes | X19: Employees in both groups reported increases in self-efficacy both from baseline to 3 and baseline to 12 months. Likewise, employees in both groups reported improved health behaviors as measured by the HPLP-IIR, in all the subscales except for one. Individuals in the WSM group did not improve in the stress management subscale from baseline to 3 months, but did improve from baseline to 12 months. Individuals in the IM groups improved at both time periods on the stress management subscale. Individuals in the WSM group improved in depression symptoms at both time periods, whereas individuals in the IM group did not improve at either time period. Participants in the WSM group reported improved health and energy levels at 3 and 12 months (all P values < 0.0001). Participants in the IM group reported improved health at 12 months (P = 0.01) and improved energy at 3 and 12 months (P = 0.0037; P = 0.0006). Participants in both groups reported their health interfered less with their personal life and work life at 3 and 12 months, compared to baseline (all P values < 0.001). Both groups also stated experiencing less difficulty with daily activities due to their health at 3 and 12 months (P values 0.0001 to 0.02), compared to baseline. No changes were observed in biometrics in either group from baseline to 3 or 12 months. | Y19: Yes | Z19: In person, telephone | AA19: 2 | AB19: Once | AC19: Self-Efficacy Theory, Social Learning Theory | AD19: Goal directed BCT Social support BCT Advise specific behaviour BCT | AE19: 3 | AF19: BCIO:007019: record behaviour without feedback BCT **NOTE: from BCTO hierarchy sheet The monitoring agent can be a human or a technical device. If recording is part of a data collection procedure rather than a strategy aimed at changing behaviour, do not code; if feedback given, code only 'provide feedback on outcome of behaviour BCT' and not this class; if observing behaviour code 'observe behaviour without feedback BCT'.
A20: Smith, Eric N., Santoro, Erik, Moraveji, Neema, Susi, Michael, Crum, Alia J. | B20: Integrating wearables in stress management interventions: Promising evidence from a randomized trial | C20: 2020 | D20: 10.1037/str0000137 10.1037/str0000137.supp (Supplemental) | E20: Effective | F20: Stress management | G20: 1 | H20: {=_xlfn.TEXTJOIN(", ", TRUE, IF(OR(ISNUMBER(SEARCH({"blood pressure","heart rate","anthropometrics","ecg","vo2max","spirometry","respiratory rate"},I20))),"Physiological", ""), IF(OR(ISNUMBER(SEARCH({"genetic"},I20))),"Risk", ""), IF(OR(ISNUMBER(SEARCH({"ultrasound","uv photog","facial","oral","CT scan"},I20))),"Imaging", ""), IF(OR(ISNUMBER(SEARCH({"glucose","hb1ac","lipids","nutrient"},I20))),"Blood", ""),IF(OR(ISNUMBER(SEARCH({"anthropometrics"},I20))),"Anthropometry", ""))} -> Physiological | I20: Respiratory rate / variability | J20: Pulmonary function | K20: 1 | L20: Randomised intervention (Note: participants had to pay $50 to enrol, which could be redeemed for "wellness" points) | M20: Adults employed at a tech company (102 control; 67 treatment; mean age = 33.2; SD = 7.8). | N20: 169 | O20: 55 | P20: 33.2 | Q20: No | R20: No | S20: 4 weeks | T20: Participants were provided with a "Spire Stone" (a monitor connected to an app which measures monitors respiratory effort and physical activity to assess metrics such as respiratory rate and respiratory rate variability, as well as steps and sedentary periods). The treatment included in-app guided breathing training modules modeled after mindfulness-based stress reduction (MBSR) programs and four wearable-based treatment components: (a) wearing of the device itself, (b) tracking and visualization of past physiological states, (c) visual real-time biofeedback, and (d) real-time notifications on significant and sustained changes of the user’s respiratory patterns. | U20: No | V20: Primary: Stress (measured with percieved stress scale [PSS]), negative symptoms of mental health such as anxiety, depression, and general distress (Mood and Anxiety Symptoms Questionnaire [MASQ]), perceived physical and mental health over time (Center for Disease Control’s Healthy Days Core and Symptoms Modules [CDC HRQOL-14]), and a single-item questionnaire about their own life-stress level. Secondary: Additional components of CDC HRQOL-14 were given to participants, to measure how many days in the past 30 days they (a) felt their mental health was not good, and (b) felt sad, blue, or depressed. Positive and negative emotions (measured via the Positive and Negative Affect Schedule), and enjoyment (measured via the Net-Promoter score). Respiratory data was alo measured. | W20: No | X20: Participants randomly assigned to the treatment group reported 15.8% fewer negative instances of stress, 13.0% fewer distressing symptoms, and 28.2% fewer days feeling anxious or stressed compared with a waitlist control. | Y20: No | Z20: Device/Online | AA20: 1 | AB20: More than once | AC20: None | AD20: Guide how to perform behaviour BCT Advise how to change emotions BCT Monitoring BCT Goal directed BCT | AE20: 4 | AF20: BCT2.4 Self-monitoring of outcome(s) of behaviour
A21: Iwahori, T., Ueshima, H., Ohgami, N., Yamashita, H., Miyagawa, N., Kondo, K., Torii, S., Yoshita, K., Shiga, T., Ohkubo, T., Arima, H., Miura, K. | B21: Effectiveness of a Self-monitoring Device for Urinary Sodium-to-Potassium Ratio on Dietary Improvement in Free-Living Adults: a Randomized Controlled Trial | C21: 2018 | D21: 10.2188/jea.JE20160144 | E21: Not effective | F21: Diet | G21: 1 | H21: {=_xlfn.TEXTJOIN(", ", TRUE, IF(OR(ISNUMBER(SEARCH({"blood pressure","heart rate","anthropometrics","ecg","vo2max","spirometry","respiratory rate"},I21))),"Physiological", ""), IF(OR(ISNUMBER(SEARCH({"genetic"},I21))),"Risk", ""), IF(OR(ISNUMBER(SEARCH({"ultrasound","uv photog","facial","oral","CT scan"},I21))),"Imaging", ""), IF(OR(ISNUMBER(SEARCH({"glucose","hb1ac","lipids","nutrient"},I21))),"Blood", ""),IF(OR(ISNUMBER(SEARCH({"anthropometrics"},I21))),"Anthropometry", ""))} -> Physiological, Blood, Anthropometry | I21: Nutrient biomarkers, anthropometrics, blood pressure | J21: Urinary sodium-to-potassium ratio | K21: 3 | L21: open, prospective, parallel RCT | M21: Adults | N21: 92 | O21: 52.2 | P21: 54.5 | Q21: No | R21: No | S21: 1 month | T21: Eligible study participants were randomly allocated into two groups. All subjects in the “device + usual care” intervention group, but not those in the “usual care” control group, were given portable handy-sized urinary Na/K ratio monitors. Participants in the intervention group were asked to measure at least one spot urine Na/K ratio daily, and to try to reduce their Na and increase their K intake to achieve a target set by investigators. All participants received a brief dietary education that provided details on how to avoid high salt foods and which vegetables and fruits could be consumed in order to increase K intake. For salt reduction, participants were given information on the top 10 Na intake sources in Japanese meals and were then advised on how to avoid these foods by replacing them with other reduced-Na alternatives. To increase the K, participants were provided with information on the major K intake sources that were available in local grocery stores. All parrticipants then received a leaflet that summarised this dietary information prior to the start of trial. | U21: Yes | V21: Primary outcome was the change in 24-hour urinary Na/K ratio (a proxy for confirming reduction in dietary salt intake). Secondary outcomes included changes in the 24-hour excretion of Na and K, BP, and body weight. | W21: No | X21: There was a non-significant trend towards larger reductions in urinary Na/K ratio observed in the intervention group, but effect of the self-monitoring device on the urinary Na/K ratio did not reach the accepted level of statistical significance on the pre-specified effect size. Changes in urinary sodium-to-potassium ratio were −0.55 in the intervention group and −0.06 in the control group (P = 0.088); respective sodium excretion changes were −18.5 mmol=24 hours and −8.7 mmol=24 hours (P = 0.528); and corresponding potassium excretion was 2.6 mmol=24 hours and −1.5 mmol=24 hours (P = 0.300). No significant reductions were observed in either blood pressure or body weight after the intervention. | Y21: No | Z21: Device/Online | AA21: 1 | AB21: More than once | AC21: None | AD21: Guide how to perform behaviour BCT Monitoring BCT | AE21: 2 | AF21: BCT2.4 Self-monitoring of outcome(s) of behaviour
A22: Wengreen, H. J., Nix, E., Madden, G. J. | B22: The effect of social norms messaging regarding skin carotenoid concentrations among college students | C22: 2017 | D22: 10.1016/j.appet.2017.04.027 | E22: Not effective | F22: Diet | G22: 1 | H22: {=_xlfn.TEXTJOIN(", ", TRUE, IF(OR(ISNUMBER(SEARCH({"blood pressure","heart rate","anthropometrics","ecg","vo2max","spirometry","respiratory rate"},I22))),"Physiological", ""), IF(OR(ISNUMBER(SEARCH({"genetic"},I22))),"Risk", ""), IF(OR(ISNUMBER(SEARCH({"ultrasound","uv photog","facial","oral","CT scan"},I22))),"Imaging", ""), IF(OR(ISNUMBER(SEARCH({"glucose","hb1ac","lipids","nutrient"},I22))),"Blood", ""),IF(OR(ISNUMBER(SEARCH({"anthropometrics"},I22))),"Anthropometry", ""))} -> Blood | I22: Nutrient biomarkers | J22: Skin carotenoid concentrations | K22: 1 | L22: randomised intervention | M22: First-year nutrition students (mean age 20, ±3.6 years) | N22: 185 | O22: 69.7 | P22: 20 | Q22: No | R22: No | S22: 7 weeks | T22: Students completed an online assessment of their usual dietary intake of FV over the past month, and were randomly assigned to the Individualized Normative Feedback group (n = 57), Manipulated Normative Feedback group (n = 62), or the Control group (n = 66). Group assignment was not disclosed to participants. As part of the course curriculum, all students were informed about the validity of skin carotenoids as a biomarker of carotenoid-containing FV consumption. Skin carotenoid levels were measured in the second week of the class and all participants were given a printed message that included the sentence, “Eating more vegetables and fruits that are red, orange, yellow, green, or purple will help to increase your skin carotenoid score.” Control group participants were told, “You will receive your skin carotenoid score in approximately 7 weeks.” Participants in the Manipulated Normative group were given a printed message that did not indicate their score, but instead said, “Your skin carotenoid score is in the 20th percentile of skin carotenoid scores for college students attending Utah State University. 80% of college students have a higher skin carotenoid score than you. Students who eat the recommended amount of fruits and vegetables have skin carotenoid scores of 35,000 or higher.” 47 of 62 (76%) students who were randomized to the Manipulated Normative group were deceived by the message communicated to them (i.e., their skin carotenoid level was not in the bottom 20% of scores among college students). Participants in the Individualized Normative group were given a printed message that included their skin carotenoid score, a visual representation of the distribution of scores measured in a reference population of “college students attending Utah State University,” and their percentile ranking within that reference distribution which was obtained from 344 students enrolled in the same course during the previous year (mean = 24,172, SD = 8697; range: 5820–52,050). For example, “Your skin carotenoid score of 32,808 is in the 82%ile of skin carotenoid scores for college students attending Utah State University. 18% of college students have a score that is higher than your score. Students who eat the recommended amount of fruits and vegetables typically have skin carotenoid scores of 35,000 or higher.” | U22: Yes | V22: Skin carotenoid concentrations, F&V consumption (self-reported). | W22: Yes | X22: Skin carotenoid levels of participants in the Manipulated Normative group increased significantly more than those in the Control group (t (126) = 3.74, p < 0.001; d = 0.67), but these students' self-reported FV intake did not increase. | Y22: No | Z22: Written Communication | AA22: 1 | AB22: Once | AC22: Focus Theory of Normative Conduct | AD22: Increase awareness of consequences BCT | AE22: 1
A23: Doets, de Hoogh, Holthuysen, Wopereis, Verain, van den Puttelaar, Hogenelst, Boorsma, Bouwman, Timmer, Pasman, van Erk, Reinders. | B23: Beneficial effect of personalized lifestyle advice compared to generic advice on wellbeing among Dutch seniors: An explorative study | C23: 2019 | D23: 10.1016/j.physbeh.2019.112642 | E23: Not effective | F23: Diet, Physical activity | G23: 2 | H23: {=_xlfn.TEXTJOIN(", ", TRUE, IF(OR(ISNUMBER(SEARCH({"blood pressure","heart rate","anthropometrics","ecg","vo2max","spirometry","respiratory rate"},I23))),"Physiological", ""), IF(OR(ISNUMBER(SEARCH({"genetic"},I23))),"Risk", ""), IF(OR(ISNUMBER(SEARCH({"ultrasound","uv photog","facial","oral","CT scan"},I23))),"Imaging", ""), IF(OR(ISNUMBER(SEARCH({"glucose","hb1ac","lipids","nutrient"},I23))),"Blood", ""),IF(OR(ISNUMBER(SEARCH({"anthropometrics"},I23))),"Anthropometry", ""))} -> Physiological, Risk, Blood, Anthropometry | I23: Blood pressure, anthropometrics, genetics, glucose, Lipids | J23: Blood pressure, body composition, genetics, glucose, lipids, weight/BMI | K23: 5 | L23: single-blind RCT | M23: Sedentary adults (age 67.7 ± 4.8 years). | N23: 59 | O23: 63 | P23: 67.7 | Q23: No | R23: No | S23: 9 weeks | T23: Participants either received personalised advice (PA) or generic advice (GA). Biological measurements were performed at baseline (T = 0) to quantify individual health status to be used in feedback for subjects in both groups (PA+GA) and as input for the decision trees to determine the content of the PA. PA was given based on metabolic health measures and dietary intake resulting in an advice that highlighted food groups and physical activity types for which behavior change was most urgent. | U23: No | V23: Self-perceived health as parameter of wellbeing using a self-perceived health score (single-item) and two questionnaires (Vita-16 and Short Form-12). Anthropometrics and physical functioning (short physical performance battery [SPPB]) were assessed. | W23: No | X23: Overall scores for self-perceived health did not change over time in any group. Resilience and motivation (Vita-16) slightly improved only in the PA group, whilst mental health (SF-12) and energy (Vita-16) showed slight improvement only in the GA group. SPPB scores improved over time in both the PA and GA group. PA participants also showed a reduction in body fat percentage and hip circumference, whereas these parameters increased in the GA group. | Y23: No | Z23: Written Communication | AA23: 1 | AB23: Once | AC23: Self-Efficacy Theory, Social Cognitive Theory | AD23: Monitoring BCT Increase awareness of consequences BCT Social Support | AE23: 3
A24: Kocher, Erica | B24: Evaluating the Feasibility and Effectiveness of Self-Monitoring of Health: a Pilot Study among Samoan Women | C24: 2019 | D24: 10.26635/phd.2020.636 | E24: Not effective | F24: Physical activity | G24: 1 | H24: {=_xlfn.TEXTJOIN(", ", TRUE, IF(OR(ISNUMBER(SEARCH({"blood pressure","heart rate","anthropometrics","ecg","vo2max","spirometry","respiratory rate"},I24))),"Physiological", ""), IF(OR(ISNUMBER(SEARCH({"genetic"},I24))),"Risk", ""), IF(OR(ISNUMBER(SEARCH({"ultrasound","uv photog","facial","oral","CT scan"},I24))),"Imaging", ""), IF(OR(ISNUMBER(SEARCH({"glucose","hb1ac","lipids","nutrient"},I24))),"Blood", ""),IF(OR(ISNUMBER(SEARCH({"anthropometrics"},I24))),"Anthropometry", ""))} -> Physiological, Anthropometry | I24: Anthropometrics | J24: Weight/BMI | K24: 1 | L24: pilot RCT | M24: Samoan women | N24: 44 | O24: 100 | P24: 36.3 | Q24: No | R24: Yes | S24: 4 weeks | T24: Two types of devices were used FitBitZip® activity monitors and BodyTrace© scales. Participants were randomly assigned to one of three groups for a four-week intervention period: 1) FitBit Zip® step-counter, 2) digital BodyTrace© scale, or 3) both devices. All participants wore FitBits for the duration of the intervention period to measure their physical activity; the screens were uncovered for the groups assigned to selfmonitor using the FitBits, but they remained covered in the Scale Only group. Participants then used the devices for a four-week intervention period. The research team visited participants once at approximately the midpoint of the four-week intervention period to download data from the FitBits. This visit did not include any additional surveys or any feedback on the outcomes of interest. | U24: No | V24: The study measured device use, daily step counts, and BMI, in addition to psychosocial indicators of health (assessed via various questionnaires: The Multidimensional Health Locus of Control Scale [HLOC] which measures an individual’s perceived control of their own health [Internal], the influence of random luck [Chance], and the influence of others such as friends, family, and medical providers [Powerful Others]; The Self-efficacy for Exercise Behaviors Scale; the Weight Efficacy Life Style Questionnaire; The SF8 Quality of Life scale; a self reported health question which asked individuals to assess their overall health for their age [Excellent, Very Good, Good, Poor, and Very Poor]. | W24: Yes | X24: There was no effect on PA levels, measured using median daily step counts. A significant increase in BMI between the baseline and post intervention assessments was observed among the two groups that used scales (Scale Only p=0.005, FitBit and Scale p=0.058), while the FitBit Only group had a slight, nonsignificant decrease in BMI (p=0.898). Post intervention the three groups did not differ in their HLOC subscale scores. Median scores on HLOC subscales increased by a statistically significant amount in the Scale Only and the combined FitBit and Scale groups. The FitBit Only group had a significant increase in the ‘Chance’ and ‘Powerful Others’ subscales, but no significant change in the Internal subscale. All three groups significantly increased their Self-efficacy for Exercise post-intervention, with a median increase in score of 16.0 points across all three groups. The FitBit Only and FitBit and Scale groups had a significant increase in Weight Control Self Efficacy following the intervention of 18.0 and 14.0 respectively, while the Scale Only group had a moderately significant increase of 12.0 (p=0.053) There was no significant difference in FibtBit use between the three groups during the baseline assessment or intervention. There was also a significant difference in self-assessed health changed during the intervention period. In the FitBit Only group SF-8 scores increased for both physical (2.5 to 6.5, p=0.002) and mental (3.0 to 6.0, p=0.008) health, indicating worsening quality of life. There were no reported changes in the SF-8 scores of the other two groups. Prior to the intevention, all participants self-reported their health as excellent, very good, or good. However, post-intervention the proportion of individuals in the FitBit only group reporting that their health was excellent increased (from 73.3% to 86.7%), while the proportion decreased for the Scale Only (64.3% to 57.1%) and FitBit and Scale groups (80.0% to 33.3%) (p=0.038). | Y24: No | Z24: Device/Online | AA24: 1 | AB24: More than once | AC24: None | AD24: Monitoring BCT | AE24: 1 | AF24: BCT2.3 Self-monitoring of behaviour
A25: Hollands, G. J., Marteau, T. M. | B25: The impact of using visual images of the body within a personalized health risk assessment: an experimental study | C25: 2013 | D25: 10.1111/bjhp.12016 | E25: Not effective | F25: Physical activity | G25: 1 | H25: {=_xlfn.TEXTJOIN(", ", TRUE, IF(OR(ISNUMBER(SEARCH({"blood pressure","heart rate","anthropometrics","ecg","vo2max","spirometry","respiratory rate"},I25))),"Physiological", ""), IF(OR(ISNUMBER(SEARCH({"genetic"},I25))),"Risk", ""), IF(OR(ISNUMBER(SEARCH({"ultrasound","uv photog","facial","oral","CT scan"},I25))),"Imaging", ""), IF(OR(ISNUMBER(SEARCH({"glucose","hb1ac","lipids","nutrient"},I25))),"Blood", ""),IF(OR(ISNUMBER(SEARCH({"anthropometrics"},I25))),"Anthropometry", ""))} -> Physiological, Anthropometry | I25: Anthropometrics | J25: Body composition, weight/BMI | K25: 1 | L25: experimental study | M25: Adults | N25: 901 | O25: 61.5 | P25: 27.2 | Q25: No | R25: No | S25: 1 month | T25: All participants received an assessment and information focusing on the health implications of internal body fat and highlighting the protective beneﬁts of PA. Participants were randomised to receive this in either (a) solely text form (control arm) or (b) text plus a visual image of predicted internal body fat (image arm). Participants received information representing one of three levels of health threat, determined by how physically active they were: high, moderate or benign. All participants recieved information on the difference between internal (intra-abdominal) and external (subcutaneous) body fat; an explanation of the link between internal fat and cardiovascular risk; and a prediction of the likely range of internal body fat the participant had. Participants in the experimental arm were presented with a visual image (standardised for each level of health risk) of what their body fat distribution might look like, additional to the text. The images used were representative of those likely to be given in feedback in health care settings, consisting of a full-body MRI scan image that was digitally manipulated to alter the visible fat distribution. Participants were informed that their risk assessment was based on a combination of baseline anthropometric and demographic details + their PA questionnaire responses. In reality (as was emphasised inthe debrieﬁng upon completion of the study), the information was based on a measure of current PA. The purpose of this basic tailoring was to provide a broadly plausible risk assessment to the recipient (i.e., ensuring that individuals who were highly physically active received benign risk information) but to retain control of the range ofinformation being communicated. By informing participants that the assessment was complex, it was intended to provide face validity and encourage engagement with the intervention. | U25: No | V25: Primary outcome measure: intention to meet recommended PA levels (assessed using a single item questionnaire). | W25: No | X25: Receipt of a visual image did not increase PA intentions overall [F(1,898) = 3.47, p = .063, r = .06]. The image intervention did signiﬁcantly increase intentions in participants who received a high level of communicated risk,(F(1,471) = 4.45, p = .035, r = .10), with no effect on those who received moderate or benign levels of communicated risk (p values > .10). The interaction between image intervention and level of communicated risk was not signiﬁcant, F(5,895) = 1.323,p = >.10. | Y25: No | Z25: Written Communication | AA25: 1 | AB25: Once | AC25: Common Sense Model, Protection Motivation Theory, Theory of Planned Behavior | AD25: Increase awareness of consequences BCT | AE25: 1
A26: Shakudo, M., Takegami, M., Shibata, A., Kuzumaki, M., Higashi, T., Hayashino, Y., Suzukamo, Y., Morita, S., Katsuki, M., Fukuhara, S. | B26: Effect of feedback in promoting adherence to an exercise programme: a randomized controlled trial | C26: 2011 | D26: 10.1111/j.1365-2753.2009.01342.x | E26: Not effective | F26: Physical activity | G26: 1 | H26: {=_xlfn.TEXTJOIN(", ", TRUE, IF(OR(ISNUMBER(SEARCH({"blood pressure","heart rate","anthropometrics","ecg","vo2max","spirometry","respiratory rate"},I26))),"Physiological", ""), IF(OR(ISNUMBER(SEARCH({"genetic"},I26))),"Risk", ""), IF(OR(ISNUMBER(SEARCH({"ultrasound","uv photog","facial","oral","CT scan"},I26))),"Imaging", ""), IF(OR(ISNUMBER(SEARCH({"glucose","hb1ac","lipids","nutrient"},I26))),"Blood", ""),IF(OR(ISNUMBER(SEARCH({"anthropometrics"},I26))),"Anthropometry", ""))} -> Physiological, Anthropometry | I26: Blood pressure, anthropometrics, VO2max | J26: Blood pressure, weight/BMI | K26: 3 | L26: RCT | M26: Adults (average age 40.5 ± 10.1 years) | N26: 105 | O26: 19 | P26: 40.5 | Q26: No | R26: No | S26: 12 weeks | T26: Study subjects were randomized into three groups (A, n = 37; B,n = 37 and C, n = 31). All subjects undertook a home-based aerobic exercise programme during the study period, which included walking, jogging and swimming at the discretion of the individual. Target exercise dose for each participant was set to meet exercise recommendations proposed by the American College of Sports Medicine (ACSM) in 1990 (aerobic exercise of more than 20 minutes per session and three sessions per week). The minimum duration of any particular exercise within a session was set at 10 minutes and aboveand exercise intensity was set at moderate intensity or higher (equivalent to 3–6 metabolic equivalents [METs] or higher). Subjects in group A were provided with feedback based on their exercise and a ‘health letter’ (newsletter on health issues every 2 weeks), while Group B was given the health letter alone every 2 weeks. Group C was a control group that was instructed to submit exercise records without any intervention. Comparison of groups A and B allowed us to evaluate whether the provision of regular feedback to participants affected their adherence, while comparison of groups B and C indicated the effect of regular contact with participants via periodic health letter. The newsletter contained general health-related topics without speciﬁc reference to the effects of exercise. | U26: No | V26: The main outcome measure throughout the study was the % achievement of target exercise level, deﬁned as the number of weeks during which the exercise target was reached divided by the number of weeks in the programme. Missing records were treated as the subject not having exercised. Secondary outcomes: BMI,SBP/DPB, Vo2max, adherence to exercise and total exercise time (in minutes) per week at 1 month after the end of the programme. Adherence was deﬁned as the maintenance of aerobic exercise for 3 or more days per week for 20 minutes per day. | W26: Yes | X26: The % achievement of target exercise level during the 12-week period was highest in group A (26.5%), followed by groups B (22.9%) and C (17.4%), but these results were non-significant (P = 0.36). In a sub-group analysis of participants under 40 compared with those over 40 years of age, % achievement of target was significantly different (*P = 0.040) between groups A (23.4%) and C (6.4%). Changes in BMI before and after the exercise programme were 0.21 kg m-2 in group A, 0.21 kg m-2 in group B and 0.05 kg m-2 in group C. Changes in SBP before and after the programme trended down-ward by 0.9 mmHg in group A (n = 30) and 2.9 mmHg in group B (n = 32), whereas that in group C (n = 29) trended upward by 1.6 mmHg. Likewise, DBP in groups A and B decreased by 0.4 and 2.3 mmHg, respectively, whereas that in Group C increased by 0.4 mmHg. Among other variables, Vo2max increased by 1.0 mL kg-1minute-1 in group A (n = 34), 1.2 mL kg-1 minute-1 in group B(n = 30) and 0.8 mL kg-1 minute-1 in group C (n = 29. No significance was provided for the secondary outcome values. | Y26: No | Z26: Device/Online | AA26: 1 | AB26: More than once | AC26: Transtheoretical Model | AD26: Monitoring BCT Goal directed BCT Increase awareness of behaviour BCT Increase awareness of consequences BCT | AE26: 4 | AF26: BCIO:007019: record behaviour without feedback BCT **NOTE: from BCTO hierarchy sheet The monitoring agent can be a human or a technical device. If recording is part of a data collection procedure rather than a strategy aimed at changing behaviour, do not code; if feedback given, code only 'provide feedback on outcome of behaviour BCT' and not this class; if observing behaviour code 'observe behaviour without feedback BCT'.
A27: Gleason-Comstock, J. A., Streater, A., Jen, K. L., Artinian, N. T., Timmins, J., Baker, S., Joshua, B., Paranjpe, A. | B27: Consumer health information technology in an adult public health primary care clinic: a heart health education feasibility study | C27: 2013 | D27: 10.1016/j.pec.2013.07.010 | E27: Not effective | F27: Alcohol reduction, Diet, smoking cessation, stress management | G27: 4 | H27: {=_xlfn.TEXTJOIN(", ", TRUE, IF(OR(ISNUMBER(SEARCH({"blood pressure","heart rate","anthropometrics","ecg","vo2max","spirometry","respiratory rate"},I27))),"Physiological", ""), IF(OR(ISNUMBER(SEARCH({"genetic"},I27))),"Risk", ""), IF(OR(ISNUMBER(SEARCH({"ultrasound","uv photog","facial","oral","CT scan"},I27))),"Imaging", ""), IF(OR(ISNUMBER(SEARCH({"glucose","hb1ac","lipids","nutrient"},I27))),"Blood", ""),IF(OR(ISNUMBER(SEARCH({"anthropometrics"},I27))),"Anthropometry", ""))} -> Physiological, Anthropometry | I27: Blood pressure, anthropometrics | J27: Blood pressure, weight/BMI | K27: 2 | L27: Randomised pre-post-follow-up design. | M27: Adults (mean age: 49.7 years, SD = 11.8]. | N27: 51 | O27: 84 | P27: 49.7 | Q27: Yes | R27: Yes | S27: 3 months | T27: Participants were randomly assigned to use a kiosk with attached devices to receive a six-week healthy eating/weight monitoring (intervention) or general health/BP monitoring (attention-control) program. Outcomes were measured at baseline, 8 weeks (post) and three month follow-up. | U27: Yes | V27: Changes in eating behavior were assessed using Rate Your Plate® (RYP), a simplified food-frequency questionnaire (FFQ) developed by the Pawtucket Heart Health Program as an eating patterns assessment and educational tool for cholesterol screening and education programs. The tool was adapted to the current population with the addition of one item related to potatoes, French fries and yams. Responses to each item were assigned values from one to three, with three indicating the healthiest behaviors for heart health. A total score was created by summing item values and could range from 31 to 93. Additional outcomes included post and follow-up blood pressure readings, weight, and BMI. | W27: Yes | X27: 27 (52%) participants completed all three assessments. Completion did not vary by group assignment: 15 were from the nutrition group and 12 from the general health group (χ2 = 0.471, p = .49). Results from multivariate analyses indicated that there were no significant differences between groups for any of the outcomes. However, regardless of group assignment, study participants showed a statistically significant reduction in both weight and blood pressure across time. Although there was an increase in healthy eating behaviors between baseline and follow-up, the change was not statistically significant. | Y27: No | Z27: Device/Online | AA27: 1 | AB27: More than once | AC27: None | AD27: Monitoring BCT Social Support | AE27: 2 | AF27: BCT2.4 Self-monitoring of outcome(s) of behaviour
A28: Proper, K. I., van der Beek, A. J., Hildebrandt, V. H., Twisk, J. W., van Mechelen, W. | B28: Short term effect of feedback on fitness and health measurements on self reported appraisal of the stage of change | C28: 2003 | D28: 10.1136/bjsm.37.6.529 | E28: Not effective | F28: Diet, Physical activity | G28: 2 | H28: {=_xlfn.TEXTJOIN(", ", TRUE, IF(OR(ISNUMBER(SEARCH({"blood pressure","heart rate","anthropometrics","ecg","vo2max","spirometry","respiratory rate"},I28))),"Physiological", ""), IF(OR(ISNUMBER(SEARCH({"genetic"},I28))),"Risk", ""), IF(OR(ISNUMBER(SEARCH({"ultrasound","uv photog","facial","oral","CT scan"},I28))),"Imaging", ""), IF(OR(ISNUMBER(SEARCH({"glucose","hb1ac","lipids","nutrient"},I28))),"Blood", ""),IF(OR(ISNUMBER(SEARCH({"anthropometrics"},I28))),"Anthropometry", ""))} -> Physiological, Blood, Anthropometry | I28: Blood pressure, anthropometrics, lipids, VO2max | J28: Blood pressure, body composition, lipids, pulmonary function | K28: 4 | L28: Randomised intervention | M28: Civil servants | N28: 299 | O28: 34.1 | P28: 44.1 | Q28: No | R28: No | S28: 9 months | T28: Participants were randomised to intervention or control groups. After fitness and health testing, intervention group participants received immediate feedback, whereas the control group did not, to determine the influence of feedback. | U28: No | V28: Stage of behaviour change (transtheoretical model) | W28: No | X28: Most of the subjects in the intervention and reference groups did not change with regard to stage of physical activity and nutrition behaviour. Only a minority in both groups reported adopting a more PA or a healthier diet, or relapsing with regard to either. However, for calorie intake and weight management, a relatively large percentage of the intervention subjects (12%) reported a relapse. The x2 test showed no significant differences between the study groups at the level of stage of behaviour change, nor did a stratified analysis for men and women. | Y28: No | Z28: In person | AA28: 1 | AB28: Once | AC28: Transtheoretical Model | AD28: Social support BCT Increase awareness of consequences BCT | AE28: 2
A29: Liukkonen, M., Nygard, C. H., Laukkanen, R. | B29: A Cluster Randomized Controlled Trial on the Effects of Technology-aided Testing and Feedback on Physical Activity and Biological Age Among Employees in a Medium-sized Enterprise | C29: 2017 | D29: 10.1016/j.shaw.2017.03.003 | E29: Not effective | F29: Physical activity | G29: 1 | H29: {=_xlfn.TEXTJOIN(", ", TRUE, IF(OR(ISNUMBER(SEARCH({"blood pressure","heart rate","anthropometrics","ecg","vo2max","spirometry","respiratory rate"},I29))),"Physiological", ""), IF(OR(ISNUMBER(SEARCH({"genetic"},I29))),"Risk", ""), IF(OR(ISNUMBER(SEARCH({"ultrasound","uv photog","facial","oral","CT scan"},I29))),"Imaging", ""), IF(OR(ISNUMBER(SEARCH({"glucose","hb1ac","lipids","nutrient"},I29))),"Blood", ""),IF(OR(ISNUMBER(SEARCH({"anthropometrics"},I29))),"Anthropometry", ""))} -> Physiological, Anthropometry | I29: Blood pressure, anthropometrics, heart rate | J29: Blood pressure, body composition, heart rate, weight/BMI | K29: 3 | L29: RCT | M29: Adult employees (mean age 42 +/- 10 years) | N29: 121 | O29: 79 | P29: 42 | Q29: No | R29: No | S29: 12 months | T29: Body Age measurement and physical activity questionnaires were conducted at 0 months, 6 months, and 12 months. The Body Age measurement process is used to form a biological age using participant's muscular strength, flexibility, aerobic fitness, and body composition. At baseline, group A received only the separate test results (not the Body Age index). Group B received the Body Age results (index in years). Group C received both Body Age and separate test results, as well as a training computer (FT60; Polar Electro Inc.) to support voluntary training. The report included all the results related to the overall population results. The participants were given a separate training program, and an occupational health nurse went through the report in detail with each participant. Between the 6th and 12th month of the intervention, all participants were contacted by phone monthly. The research nurse called them to complete the physical activity questionnaire and provided guidance if needed. | U29: Yes | V29: Biological age reduction measured using BodyAge, and physical activity estimates using the International Physical Activity Questionnaire Short Form (IPAQ-SF). | W29: Yes | X29: The Body Age difference decreased significantly during the intervention, however, no interaction effect was found. The mean changes (years) in the groups were as follows: A −2.20 [95% confidence interval (CI): −3.09 to −1.30], B −2.83 (95% CI: –3.76 to −1.91), and C −2.31 (95% CI: –3.24 to −1.37). While changes over time were statistically significant in all groups (p < 0.001), there were no statistically significant differences in the changes between the groups (p = 0.13). There were significant differences in PA levels between the groups (p = 0.027), however the changes were not significant (p = 0.98) and with no interaction effects (p = 0.63). The mean changes (MET/min/wk) in the groups, from baseline to the end, were as follows: A −89 (95% CI: –1,109 to 926), B −17 (95% CI: –1,021 to 987), and C 127 (95% CI: –904 to 1,158). The paper also mentions SBP improved significantly but there are no detailed results indicating this in the body of the paper, nor in the supplementary files. | Y29: No | Z29: Telephone | AA29: 1 | AB29: More than once | AC29: None | AD29: Social support BCT | AE29: 1
A30: Damschroder, L. J., Buis, L. R., McCant, F. A., Kim, H. M., Evans, R., Oddone, E. Z., Bastian, L. A., Hooks, G., Kadri, R., White-Clark, C., Richardson, C. R., Gierisch, J. M. | B30: Effect of Adding Telephone-Based Brief Coaching to an mHealth App (Stay Strong) for Promoting Physical Activity Among Veterans: Randomized Controlled Trial | C30: 2020 | D30: 10.2196/19216 | E30: Not effective | F30: Physical activity | G30: 1 | H30: {=_xlfn.TEXTJOIN(", ", TRUE, IF(OR(ISNUMBER(SEARCH({"blood pressure","heart rate","anthropometrics","ecg","vo2max","spirometry","respiratory rate"},I30))),"Physiological", ""), IF(OR(ISNUMBER(SEARCH({"genetic"},I30))),"Risk", ""), IF(OR(ISNUMBER(SEARCH({"ultrasound","uv photog","facial","oral","CT scan"},I30))),"Imaging", ""), IF(OR(ISNUMBER(SEARCH({"glucose","hb1ac","lipids","nutrient"},I30))),"Blood", ""),IF(OR(ISNUMBER(SEARCH({"anthropometrics"},I30))),"Anthropometry", ""))} -> Physiological, Anthropometry | I30: Heart rate, anthropometrics | J30: Heart rate, weight/BMI | K30: 2 | L30: Randomized Controlled Trial (RCT) | M30: US veterans (aged 39.8, SD 8.7) | N30: 350 | O30: 25.2 | P30: 39.8 | Q30: Yes | R30: Yes | S30: 12 months | T30: Half the participants were randomised to the "Stay Strong" app alone (n=179), and half to "Stay Strong+Coaching" (n=178); both programs lasted 12 months. Stay Strong+Coaching utilised personalised coaching via automated in-app motivational messages (3 per week), telephone-based human health coaching (up to 3 calls), and personalised weekly goal setting. All aspects of the enrollment process and program delivery were accomplished virtually for both groups, except for the telephone-based coaching. | U30: Yes | V30: The primary outcome was change in physical activity at 12 months post-baseline, measured by average weekly Active Minutes, captured by the Fitbit Charge 2 device. Secondary outcomes included changes in step counts, weight, and patient activation. | W30: Yes | X30: Active Minutes decreased from baseline to 12 months for both groups (P<.001) with no between-group differences at 6 months (P=.82) or 12 months (P=.98). However, at 12 months, many participants in both groups did not record Active Minutes, leading to missing data in 67.0% (120/179) for Stay Strong and 61.8% (110/178) for Stay Strong+Coaching. Average baseline weight for participants in Stay Strong and Stay Strong+Coaching was 214 lbs and 198 lbs, respectively, with no difference at baseline (P=.54) or at 6 months (P=.28) or 12 months (P=.18) post-baseline based on administrative weights, which had lower rates of missing data. Changes in the number of steps recorded and patient activation also did not differ by arm. Adding automated and phone-based human coaching to the Stay Strong mHealth program (Stay Strong+Coaching) did not improve PA levels compared to baseline, nor compared to the Stay Strong program alone among US veterans. Specifically, the rate of changes did not show difference between arms in Active Minutes, step counts, patient activation, and weight at 6 months or 12 months. In Stay Strong+Coaching, 70.8% (126/178) of participants completed at least 2 of 3 planned coaching calls in the first 9 weeks of the program but, like participants in Stay Strong, significantly decreased the frequency of syncing their Fitbit device to the point where over 60% (230/357) of trial participants had missing PA data 12 months postbaseline. | Y30: No | Z30: Device/Online, Telephone | AA30: 2 | AB30: More than once | AC30: IMB Model, Self-Regulation Theory, The BUS Framework | AD30: Goal directed BCT Social support BCT Increase awareness of behaviour BCT | AE30: 3 | AF30: BCT2.3 Self-monitoring of behaviour BCT2.4 Self-monitoring of outcome(s) of behaviour
A31: Knight, E., Stuckey, M. I., Petrella, R. J. | B31: Health promotion through primary care: enhancing self-management with activity prescription and mHealth | C31: 2014 | D31: 10.3810/psm.2014.09.2080 | E31: Not effective | F31: Physical activity | G31: 1 | H31: {=_xlfn.TEXTJOIN(", ", TRUE, IF(OR(ISNUMBER(SEARCH({"blood pressure","heart rate","anthropometrics","ecg","vo2max","spirometry","respiratory rate"},I31))),"Physiological", ""), IF(OR(ISNUMBER(SEARCH({"genetic"},I31))),"Risk", ""), IF(OR(ISNUMBER(SEARCH({"ultrasound","uv photog","facial","oral","CT scan"},I31))),"Imaging", ""), IF(OR(ISNUMBER(SEARCH({"glucose","hb1ac","lipids","nutrient"},I31))),"Blood", ""),IF(OR(ISNUMBER(SEARCH({"anthropometrics"},I31))),"Anthropometry", ""))} -> Physiological, Blood, Anthropometry | I31: Blood pressure, glucose, anthropometrics | J31: Blood pressure, glucose, weight/BMI | K31: 3 | L31: randomised intervention | M31: Adults (mean age 63 ± 5 years) | N31: 45 | O31: 55.6 | P31: 63 | Q31: No | R31: No | S31: 12 weeks | T31: Tailored physical activity prescription targeting changes in various intensities of physical activity (eg, exercise, sedentary behavior, or both) for improving physiological and behavioral markersof lifestyle-related disease risk. Participants were randomly assigned to one of three groups; (1) exercise (EX), in which participants received PA prescription targeting increases in high-intensity activity (ie, exercise); (2) sedentary behavior (SB),in which participants received a physical activity prescription targeting reductions and interruptions in low-intensity daily activity (ie, sedentary behavior); and (3) comprehensive counseling (CC), in which participants received an activity prescription targeting both increases in high-intensity activity (ie, exercise) and reductions in low-intensity activity (ie, sedentary behavior). All participants received an mHealth technology kit including smartphone, blood pressure monitor, glucometer, and pedometer. Participants engaged in physical activity programming at home during the 12-week intervention period. | U31: No | V31: Physical activity (steps) was measured daily. Body weight (kg) was measured once weekly using the participant’s own weight scale. Blood pressure (mm Hg) was measured in a seated position 3 times weekly (2 weekdays and 1 weekend day) upon waking. Fasting blood glucose (mmol/L) was measured once weekly. | W31: Yes | X31: The multivariate analysis of variance revealed a significant effect of the intervention during the 12-week home-monitoring period F(10 488) = 2.947, P = 0.001, ηP2 = 0.057). Changes in home-monitored body weight varied across groups from a non-significant reduction in the SB group (-0.8kg, P0.52), to a significant increase in the EX (+2.8kg, P 0.02) and a non-significant increase in the CC group (+0.7kg, P0.54). However, there was no significant difference in these changes when between-group analysis was performed. Mean home-monitored systolic blood pressure was reduced by 4.2 mm Hg and diastolic blood pressure by 4.0 mm Hg, with reductions in systolic and diastolic blood pressure reaching significant across all groups. These values may be considered clinically meaningful. Mean changes in blood glucose were significant for the groups prescribed higher intensity activity (EX: -0.4mmol/L and CC: -0.8mmol/L).There was no significant difference in changes between groups for physical activity (F(2247) = 1.615, P = 0.201, ηP2 = 0.013), or blood pressure (systolic, F(2247) = 1.260, P = 0.286, ηP2 = 0.010; diastolic,F(2247) = 0.520, P = 0.595, ηP2 = 0.004). Changes were significantly different between groups for fasting blood glucose (F(2247) = 5.978, P = 0.003, ηP2 = 0.046). | Y31: No | Z31: Device/Online | AA31: 1 | AB31: More than once | AC31: None | AD31: Increase awareness of behaviour BCT Guide how to perform behaviour BCT Monitoring BCT | AE31: 3 | AF31: BCT2.3 Self-monitoring of behaviour BCT2.4 Self-monitoring of outcome(s) of behaviour
A32: Hietaranta-Luoma, H. L., Tahvonen, R., Iso-Touru, T., Puolijoki, H., Hopia, A. | B32: An intervention study of individual, apoE genotype-based dietary and physical-activity advice: impact on health behavior | C32: 2014 | D32: 10.1159/000371743 | E32: All groups improved | F32: Alcohol reduction, Diet, Physical activity | G32: 3 | H32: {=_xlfn.TEXTJOIN(", ", TRUE, IF(OR(ISNUMBER(SEARCH({"blood pressure","heart rate","anthropometrics","ecg","vo2max","spirometry","respiratory rate"},I32))),"Physiological", ""), IF(OR(ISNUMBER(SEARCH({"genetic"},I32))),"Risk", ""), IF(OR(ISNUMBER(SEARCH({"ultrasound","uv photog","facial","oral","CT scan"},I32))),"Imaging", ""), IF(OR(ISNUMBER(SEARCH({"glucose","hb1ac","lipids","nutrient"},I32))),"Blood", ""),IF(OR(ISNUMBER(SEARCH({"anthropometrics"},I32))),"Anthropometry", ""))} -> Risk | I32: Genetics | J32: ApoE allele | K32: 1 | L32: single-blinded intervention study | M32: Healthy adults (mean age 47.0, SD 12.1) | N32: 107 | O32: 69.2 | P32: 47 | Q32: No | R32: No | S32: 12 months | T32: Participants were randomised into control (n = 61) and intervention groups (n = 61) using the random sampling method of Microsoft Excel. Of the 61 subjects in the intervention group, 40 were placed in the low-risk (Ɛ4–) and 21 in the high-risk (Ɛ4+) group. Due to drop-outs, 107 subjects were included in final analysis. Baseline and follow-up assessments included detailed measurements of psychological, behavioral, and clinical factors. During the intervention, 6 different communication sessions were arranged. The 1st session was a compulsory lecture on healthy lifestyle and diet held by a qualified nutritionist. The 2nd and 5th sessions included health messages and information on the personal apoE genotype provided by mail. The 3rd session was an elective lecture on gene-diet interactions and apoE held by a professor of nutrigenomics and nutrigenetics. Finally, the 4th and 6th communication sessions were voluntary personal discussions with the doctor. These two sessions were carried out according to the guidelines for scientific practice laid down in the Declaration of Helsinki. Health behavioral effects were assessed for the Ɛ4+ (n = 16) and Ɛ4– (n = 35) intervention groups as well as for the control group (n = 56). The genotypes apoE 3/4 (n = 15) and 4/4 (n = 1) were included in group Ɛ4+, and the genotypes 2/3 (n = 8) and 3/3 (n = 27) were included in group Ɛ4–. In the control group, the participants had the genotypes 3/4 (n = 11), 4/4 (n = 1), 2/3 (n = 6), 3/3 (n = 37), and 2/2 (n = 1). Genotype apoE 2/4 did not occur in the participants. Health information was based on the analyzed apoE genotype and was provided using the Extended Parallel Process Model (EPPM) . The specific risk communicated to the participants in the study was CVD, and the effect of apoE genotype on CVD risk was emphasized for each participant in the intervention groups. For the Ɛ4+ group, the message emphasized that a dietary change (e.g., improvement in fat quality) and increased exercise would be especially important for their genotype in order to lower the cholesterol level and prevent CVD. The information for the Ɛ4– group emphasized the interaction between environmental factors and genotype and highlighted the significance of the individual’s own lifestyle. All tailored health information comprised four different parts: response efficacy, self-efficacy, susceptibility, and severity . The control group received general information about the study together with general health information on lifestyle and CVD risk based on health and nutrition recommendations and studies from the National Institute for Health and Welfare in Finland. | U32: Yes | V32: Behavioral changes were measured by diet (e.g., fat quality, as well as consumption of vegetables, berries, fruits, and fatty and sugary foods), alcohol consumption, and exercise, indicated via questionnaires. Additionally health and taste attitudes were assessed with the Health and Taste Attitude Scales (HTAS). | W32: Yes | X32: Saturated fat intake was higher than recommended in every group (scores: 10–17) at baseline (T0). Intake of unsaturated fat increased and that of saturated fat decreased in every group after the genetic feedback (T1). The change was greatest in the Ɛ4+ group (ΔT0–T1: +3.8), and there was a statistically significant difference between the Ɛ4+ and the control group (p < 0.05, partial η 2 = 0.064) ( table 3 ; fig. 2 ). Every group improved the fat quality in their diet until the 6-month measuring point (T2), but the improvement (T0–T2) was significant (p < 0.01, partial η 2 = 0.125) only in the Ɛ4+ group. Towards the end of the intervention and during the last 6 months with no active health communication (T3), the intake of saturated fat again increased and that of unsaturated fat decreased in both intervention groups. This unfavorable change in scores was higher in the Ɛ4+ group (ΔT2–T3: –1.7) than in the Ɛ4– group (ΔT2–T3: –0.2). In the control group, fat quality improved slightly even during the last 6 months of the intervention (ΔT2–T3: +0.2). Although the dietary fat quality deteriorated during the last 6 months of the intervention, the fat quality of the diet was improved at the end of the intervention (T3) compared with the baseline values (T0) for every group. However, this total improvement (T0–T3) was not significant in any group. Vegetable, fruit, and berry consumption increased slightly in every group during the intervention, but the differences between the groups were minor and not statistically significant. There was a decreasing trend in the consumption of high-fat/high-sugar foods. During the intervention, the changes in alcohol consumption after the disclosure of personal genetic information were minor, and there were no statistically significant differences between the groups. Genetic feedback had only a minor impact on physical activity. The biggest difference was ΔT0–T1 between the Ɛ4+ and the Ɛ4– group. Physical activity increased by 6.3% in the Ɛ4+ group but decreased by 17.1% in the Ɛ4– group; however, the difference was not significant. There was an increasing trend toward the valuation of health (general health interest, light product interest, and natural product interest) and a decreasing trend toward the valuation of taste (craving for sweet foods, using food as a reward, and pleasure) in every group after the genetic feedback (T1), especially in the Ɛ4+ group ( table 4 ). The reliability of the HTAS was acceptable, with α coefficient values of 0.73 (T0), 0.76 (T1), 0.72 (T2), and 0.70 (T3). | Y32: No | Z32: In person | AA32: 1 | AB32: More than once | AC32: Extended Parallel Process Model | AD32: Increase awareness of behaviour BCT | AE32: 1
A33: Roke, K., Walton, K., Klingel, S. L., Harnett, A., Subedi, S., Haines, J., Mutch, D. M. | B33: Evaluating changes in omega-3 fatty acid intake after receiving personal FADS1 genetic information: A randomized nutrigenetic intervention | C33: 2017 | D33: 10.3390/nu9030240 | E33: All groups improved | F33: Diet | G33: 1 | H33: {=_xlfn.TEXTJOIN(", ", TRUE, IF(OR(ISNUMBER(SEARCH({"blood pressure","heart rate","anthropometrics","ecg","vo2max","spirometry","respiratory rate"},I33))),"Physiological", ""), IF(OR(ISNUMBER(SEARCH({"genetic"},I33))),"Risk", ""), IF(OR(ISNUMBER(SEARCH({"ultrasound","uv photog","facial","oral","CT scan"},I33))),"Imaging", ""), IF(OR(ISNUMBER(SEARCH({"glucose","hb1ac","lipids","nutrient"},I33))),"Blood", ""),IF(OR(ISNUMBER(SEARCH({"anthropometrics"},I33))),"Anthropometry", ""))} -> Risk | I33: Genetics | J33: SNPs in FADS1 and omega-3 metabolism | K33: 1 | L33: Randomised intervention | M33: Females (mean age = 22.0 ± 1.5 years). | N33: 57 | O33: 100 | P33: 22 | Q33: No | R33: No | S33: 12 weeks | T33: Participants were randomised into either a Genetic group (intervention) or Non-Genetic group (control), ensuring that each group would have an equivalent number of major and minor allele carriers. The lead investigator for the study intervention was blinded to this assignment. Participants were informed of which group they were in at baseline. Participants provided fasted blood samples, had a one-on-one information session, and received a copy of all study intervention materials. All participants were also given a generic information document that provided details of omega-3 FAs, and an overview of the association between SNPs in FADS1 and omega-3 metabolism. Specifically, it was indicated that individuals who are homozygote GG allele carriers have been reported to have more EPA in their bodies and an increased ability to convert ALA into EPA and DHA, while individuals with at least one copy of the minor allele (GT or TT) were shown to have less EPA in their bodies and a reduced ability to convert ALA into EPA and DHA.If participants were assigned to the Genetic group, they were informed they were either a major (GG) or minor (GT + TT) allele carrier, according to their personal FADS1 genotype. If the participants were in the Non-Genetic group, the letter indicated that they would receive their genetic information at the end of the study. Importantly, no dietary advice was provided in a genotype-specific manner. | U33: No | V33: Dietary intake of omega-3 FAs was assessed via FFQ. Data on the awareness of omega-3 FAs, perceptions of receiving genetic information, and overall perceptions of the study intervention was also assessed through online questionnaires with questions of various types (multiple choice, select all that apply, Likert-style rating questions, sliding bar scales, and open text boxes). | W33: Yes | X33: The intervention did not differentially influence dietary intake of EPA and DHA (p = 0.27), however, both groups significantly increased their intake of EPA and DHA during the intervention (p = 1.0 × 10−4). At the end of the study intervention, %EPA increased similarly in both groups (p = 0.02). Both groups experienced small increases in Total cholesterol, the Chol/HDL ratio, LDL and Non-HDL from Baseline to Final (Table 2). The change in the Chol/HDL ratio was not significant after correction for multiple comparisons. When asked about consumption of omega-3 foods, there were 8, 5 and 15 individuals in the Genetic Group, and 6, 9, and 13 in the Non-Genetic group who said “yes”, “no” and “sometimes” to making changes to overall omega-3 consumption in their diet, respectively. Participants who said “yes” or “sometimes” were then asked a subsequent question about the factors contributing to their dietary changes. There were 8/28 (28.6%) in the Genetic Group and 5/28 (17.9%) in the Non-Genetic group who reported that the reason for their dietary changes were related to the generic omega-3 information document provided to them at the start of the study (p = 0.09). However, there were 5/28 (17.9%) individuals in the Genetic group who reported that their personal genetic information was the reason they made changes to their diet. | Y33: No | Z33: Written Communication | AA33: 1 | AB33: Once | AC33: None | AD33: Goal directed BCT Increase awareness of consequences | AE33: 2
A34: Leskinen, H. M., Tringham, M., Karjalainen, H., Iso-Touru, T. K., Hietaranta-Luoma, H. L., Marnila, P. J., Pihlava, J. M., Hurme, T., Kankaanpaa, S. J., Puolijoki, H., Akerman, K., Tanner, L., Sandell, M., Vahakangas, K., Hopia, A., Tahvonen, R., Rokka, L. S. | B34: APOE Genotype Disclosure and Lifestyle Advice in a Randomized Intervention Study with Finnish Participants | C34: 2021 | D34: 10.1093/jn/nxaa316 | E34: All groups improved | F34: Diet, Physical activity | G34: 2 | H34: {=_xlfn.TEXTJOIN(", ", TRUE, IF(OR(ISNUMBER(SEARCH({"blood pressure","heart rate","anthropometrics","ecg","vo2max","spirometry","respiratory rate"},I34))),"Physiological", ""), IF(OR(ISNUMBER(SEARCH({"genetic"},I34))),"Risk", ""), IF(OR(ISNUMBER(SEARCH({"ultrasound","uv photog","facial","oral","CT scan"},I34))),"Imaging", ""), IF(OR(ISNUMBER(SEARCH({"glucose","hb1ac","lipids","nutrient"},I34))),"Blood", ""),IF(OR(ISNUMBER(SEARCH({"anthropometrics"},I34))),"Anthropometry", ""))} -> Physiological, Risk, Anthropometry | I34: Genetics, anthropometrics, blood pressure | J34: APOE genotype | K34: 3 | L34: Randomised intervention trial | M34: Healthy volunteers (mean ± SD age: 51.0 ± 5.6 y) | N34: 188 | O34: 82.4 | P34: 51 | Q34: No | R34: Yes | S34: 18 months | T34: APOE ε4 allele is associated with higher risks of cardiovascular diseases and Alzheimer disease than ε3 and ε2 - dietary and lifestyle guidance and personal genetic risk information [ε4 carrier (ε4+); ε4 noncarrier (ε4−)] as motivators. participants were genotyped for APOE and divided into intervention (INT; INTε4+, n = 33; INTε4−, n = 57) and control groups (CTRL; CTRLε4+, n = 36; CTRLε4−, n = 62). Blood samples, measured observations, and questionnaire data were obtained at baseline and at 1 and 1.5 y. INT participants received their ε4 carrier status at baseline. Monthly Internet-based guidance based on the Finnish Dietary guidelines was provided for all. | U34: No | V34: Measures taken at baseline (T0), 1-y follow-up (T1), and 1.5-y follow-up (T1.5) included anthropometric measures, BP, and blood samples. The participants were also interviewed regarding their medication, chronic illnesses, recent respiratory infections, and dietary supplement use. Preceding each sampling, the participants were requested to keep a 7-d physical activity diary and a 4-d food diary, mainly for self-monitoring purposes. All the other variables except the self-reported lifestyle variables were measured by the research staff, and participants were requested to fill in a lifestyle questionnaire after each sampling event. The participants received results concerning their general clinical biomarkers, serum lipids, and glucose tolerance markers after each sampling event for self-monitoring purposes. | W34: Yes | X34: Self-reported dietary fat quality scores of all the participants were higher (i.e., fat quality was improved) at T1 and T1.5 than at T0 (P = 0.015, increase from 18.0 at T0 to 18.9 at T1 and T1.5). Fruits, vegetables, and berry consumption increased among all the participants from 3.5 portions/d at T0 to 3.7 portions/d at T1 and 3.6 portions/d at T1.5 (P = 0.015). Vegetable consumption was higher in INTε4+ than in INTε4−, but no differences were observed between CTRLε4− and CTRLε4+ (P-interaction = 0.044). High-fat and -sugar food consumption decreased for all the participants, from 7.3 portions/wk at T0 to 6.4 and 6.5 portions/wk at T1 and T1.5, respectively (P = 0.007), and was higher in INT than in CTRL (P = 0.009). Fish intake did not differ between groups, but there was a close to significant (P = 0.11) increase in the proportion of participants (from 20.0% to 25.4%) consuming fish at least twice a week (Table 3). Physical activity level tended to be higher in ε4+ than in ε4− (P = 0.095). Alcohol intake over time did not change (P = 0.71, data not shown) but was lower in INT than in CTRL at T1.5 (P= 0.019). | Y34: No | Z34: Device/Online | AA34: 1 | AB34: More than once | AC34: None | AD34: Increase awareness of behaviour BCT Monitoring BCT Social support BCT | AE34: 3 | AF34: BCT2.3 Self-monitoring of behaviour
A35: Homma, S., Imamura, H., Nakamura, T., Fujimura, K., Ito, Y., Maeda, Y., Kaneko, I. | B35: A comparative study on the effectiveness of one-way printed communication versus videophone interactive interviews on health promotion | C35: 2016 | D35: 10.1177/1357633X15587436 | E35: All groups improved | F35: Diet, Physical activity | G35: 2 | H35: {=_xlfn.TEXTJOIN(", ", TRUE, IF(OR(ISNUMBER(SEARCH({"blood pressure","heart rate","anthropometrics","ecg","vo2max","spirometry","respiratory rate"},I35))),"Physiological", ""), IF(OR(ISNUMBER(SEARCH({"genetic"},I35))),"Risk", ""), IF(OR(ISNUMBER(SEARCH({"ultrasound","uv photog","facial","oral","CT scan"},I35))),"Imaging", ""), IF(OR(ISNUMBER(SEARCH({"glucose","hb1ac","lipids","nutrient"},I35))),"Blood", ""),IF(OR(ISNUMBER(SEARCH({"anthropometrics"},I35))),"Anthropometry", ""))} -> Physiological, Blood, Anthropometry | I35: Blood pressure, anthropometrics, lipids, glucose, HbA1c | J35: Blood pressure, weight/BMI, lipids, glucose, HbA1c | K35: 5 | L35: Randomised intervention trial | M35: Adults (mean age 66.1, SD 1.98) | N35: 68 | O35: 65 | P35: 66.1 | Q35: No | R35: No | S35: 3 months | T35: Participants were randomised into two groups: one group received individualized monthly documented reports (DR) (n = 33; 22 females; average age: 67.2 years), and the other received interactive videophone communication (IVC) (n = 35; 22 females; average age: 65.1 years) for three months. Telemonitoring was conducted on both groups, using a pedometer, weighing scale and a sphygmomanometer. Pre- and post-intervention, anthropometric measurements and blood tests were performed; the participants also completed self-administered questionnaires. In the videophone group, the duration of the counselling session was pre-determined and, as previously mentioned, was set at 20 minutes for the first and last sessions, and 15 minutes for the intervening session. One doctor delivered the consultation that occurred via videophone at all the sessions. In the document group, one consultant medical doctor, who also acted as a consultant in the videophone group, could prepare the counselling report at any time, and was not restricted by a pre-scheduled time. The mean time spent on the preparation of the first and last reports per participant was 9.2 ± 0.3 minutes. For the intervening report, the mean time spent on the preparation of the report per participant was 6.7 ± 0.2 minutes. | U35: Yes | V35: Blood biochemistry (lipids, glucose, HbA1c, albumin, uric acid, creatinine, blood urea nitrogen [BUN], protein), BP, PA determined by daily step count, BMI. Changes to behaviour and "stage of behavioural change" were measured via questionnaire. | W35: Yes | X35: The average number of steps per day during the last month in both groups was significantly higher than the first month (DR average increase = 946 steps, IVC = 1,495 steps). The difference between groups was not statistically significant. Most clinical parameters had non-significant improvements in both intervention groups. There was a small significant decrease in post-intervention BMI in DR group (-0.6kg/m2), but not in the IVC group. Diastolic blood pressure significantly decreased in the IVC group only (-7.6mmHg). Self-assessment of stage of behavioural modification (according to transtheoretical model) indicated significant improvements in stage of behaviour change in PA and dietary habits in the videophone group. In contrast, the document group showed improvement in stage of behaviour change with regard to PA only. Regarding lifestyle change as a result of participation in the programme, 72.7% of the document group and 97.1% of the videophone group answered, ‘Yes’; this difference was significant (P = 0.005). | Y35: No | Z35: Telephone | AA35: 1 | AB35: More than once | AC35: Transtheoretical Model | AD35: Increase awareness of behaviour BCT | AE35: 1
A36: Vassy, J. L., Christensen, K. D., Schonman, E. F., Blout, C. L., Robinson, J. O., Krier, J. B., Diamond, P. M., Lebo, M., Machini, K., Azzariti, D. R., Dukhovny, D., Bates, D. W., MacRae, C. A., Murray, M. F., Rehm, H. L., McGuire, A. L., Green, R. C., MedSeq, Project | B36: The Impact of Whole-Genome Sequencing on the Primary Care and Outcomes of Healthy Adult Patients: A Pilot Randomized Trial | C36: 2017 | D36: 10.7326/M17-0188 | E36: All groups improved | F36: Diet, Physical activity, medication changes, supplement changes | G36: 4 | H36: {=_xlfn.TEXTJOIN(", ", TRUE, IF(OR(ISNUMBER(SEARCH({"blood pressure","heart rate","anthropometrics","ecg","vo2max","spirometry","respiratory rate"},I36))),"Physiological", ""), IF(OR(ISNUMBER(SEARCH({"genetic"},I36))),"Risk", ""), IF(OR(ISNUMBER(SEARCH({"ultrasound","uv photog","facial","oral","CT scan"},I36))),"Imaging", ""), IF(OR(ISNUMBER(SEARCH({"glucose","hb1ac","lipids","nutrient"},I36))),"Blood", ""),IF(OR(ISNUMBER(SEARCH({"anthropometrics"},I36))),"Anthropometry", ""))} -> Risk | I36: Genetics | J36: Genetic monogenic disease risk (MDR) results, carrier variants, pharmacogenomic associations, and polygenic risk estimates for cardiometabolic traits | K36: 1 | L36: Pilot randomised trial | M36: Generally healthy patients aged 40–65. | N36: 100 | O36: 58 | P36: 55 | Q36: Yes | R36: Yes | S36: 6 months | T36: Patients were randomly assigned to receive a family history report alone (FH arm) or in combination with an interpreted WGS report including monogenic disease risk (MDR) results (associated with Mendelian disorders), carrier variants, pharmacogenomic associations, and polygenic risk estimates for cardiometabolic traits (FH+WGS arm). Each patient met with his or her PCP to discuss the reports. | U36: Yes | V36: Primary outcomes: healthcare utilisation, anxiety and depression (measured by the 14-item Hospital Anxiety and Depression Scale [HADS]), and self-reported health status (measured on a 5-item Likert scale). The six-month survey also included the following health behavior question: “Have you made any of the following health or wellness changes that were specifically motivated by the information you discussed with your doctor?”. Response options included diet, exercise, use of vitamins/herbal supplements, use of medications, and other. Also included were molecular and clinical diagnoses. | W36: Yes | X36: 30% (17%–45%) and 41% (27%–56%) of FH and FH+WGS patients, respectively, reported making a health behavior change after six months (mostly exercise [16 and 27%] and diet [20 and 33%]). | Y36: No | Z36: Written Communication | AA36: 1 | AB36: Once | AC36: None | AD36: Increase awareness of behaviour BCT Social support BCT | AE36: 2
AE37: 2
A38: Papers from Hollands et al., 2022 DOI:10.1371/journal.pmed.1003920
A39: Whitehead, R. D., Ozakinci, G., & Perrett, D. I. | B39: A Randomized Controlled Trial of an Appearance-Based Dietary Intervention | C39: 2014 | D39: 10.1037/a0032322 | E39: Effective | F39: Diet | G39: 1 | H39: {=_xlfn.TEXTJOIN(", ", TRUE, IF(OR(ISNUMBER(SEARCH({"blood pressure","heart rate","anthropometrics","ecg","vo2max","spirometry","respiratory rate"},I39))),"Physiological", ""), IF(OR(ISNUMBER(SEARCH({"genetic"},I39))),"Risk", ""), IF(OR(ISNUMBER(SEARCH({"ultrasound","uv photog","facial","oral","CT scan"},I39))),"Imaging", ""), IF(OR(ISNUMBER(SEARCH({"glucose","hb1ac","lipids","nutrient"},I39))),"Blood", ""),IF(OR(ISNUMBER(SEARCH({"anthropometrics"},I39))),"Anthropometry", ""))} -> Imaging | I39: Facial skin appearance | J39: Facial skin appearance | K39: 1 | L39: preliminary RCT | M39: Adults (mean age = 23.01, age range: 18–61) | N39: 73 | O39: 67 | P39: 23 | Q39: No | R39: No | S39: 10 weeks | T39: Two appearance-based dietary interventions were evaluated against a control group: one demonstrated the effect of increased and decreased fruit and vegetable consumption on an image of the participant’s own face, and the second demonstrated the same skin colour effects on generic young adult faces. Subjects were randomly allocated to one of three conditions (n = 25, 23, 25 for information-only, generic appearance, and own-face appearance intervention groups, respectively). Participants in generic face group were presented with stimuli constructed by averaging the facial shape and colour of four males or females. Both resulting base faces were manipulated in colour according to the spectrophotometer-derived effect of a 6-week change in consumption of fruit and vegetables. Participants could advance through the fruit and vegetable skin colour continuum and were instructed to select the healthiest face color on two trials. The experimenter then explained how increased fruit and vegetable consumption changed skin colour and that, in independent experiments, this made the faces appear healthier and more attractive. Participants were told the approximate difference in fruit and vegetable consumption between the baseline and the skin color they found healthiest. Participants in the "own face" group received similar materials to the generic appearance intervention group, but illustrations were performed on images of each participant’s own face. Participants viewed a demonstration (as above) in which they were able to manipulate the colour of their own face according to the empirically derived fruit and vegetable skin colour axis. These participants were asked to select what they perceived to be closest to their current skin color on two trials, followed by two trials selecting what they perceived to be the healthiest skin color from the available range. Participants received a leaflet, identical to that given to the generic appearance intervention group, except that the images were of the participant’s own face. | U39: No | V39: Change in fruit and vegetable consumption | W39: Yes | X39: 46 participants (information-only 17, generic appearance 11, own-face appearance 18) completed an average of 9.6 (± 0.68 SD) follow-up questionnaires. Controlling for baseline consumption, the own-face appearance group reported a significant increase in their post-baseline fruit and vegetable consumption from baseline compared with the information-only group in post hoc tests (Bonferroni-corrected, p = .042). No other groups differed significantly (p > = .147). The own-face appearance intervention group reported a significant increase in their post-baseline (average of 10 postbaseline reports) fruit and vegetable consumption from baseline (Bonferroni-corrected, t(17) = −2.726, p = .042, dz = 0.65). The other groups did not report significant diet change (p > = .534). | Y39: No | Z39: In person, written communication | AA39: 2 | AB39: Once | AC39: None | AD39: Increase awareness of consequences BCT Outcome consequence BCT | AE39: 2
A40: Araújo M-R, Alvarez M-J, Godinho CA, Roberto MS | B40: An eight-month randomized controlled trial on the use of intra-oral cameras and text messages for gingivitis control among adults | C40: 2018 | D40: 10.1111/idh.12391 | E40: Effective | F40: Oral health behaviour | G40: 1 | H40: {=_xlfn.TEXTJOIN(", ", TRUE, IF(OR(ISNUMBER(SEARCH({"blood pressure","heart rate","anthropometrics","ecg","vo2max","spirometry","respiratory rate"},I40))),"Physiological", ""), IF(OR(ISNUMBER(SEARCH({"genetic"},I40))),"Risk", ""), IF(OR(ISNUMBER(SEARCH({"ultrasound","uv photog","facial","oral","CT scan"},I40))),"Imaging", ""), IF(OR(ISNUMBER(SEARCH({"glucose","hb1ac","lipids","nutrient"},I40))),"Blood", ""),IF(OR(ISNUMBER(SEARCH({"anthropometrics"},I40))),"Anthropometry", ""))} -> Imaging | I40: Imaging oral health | J40: Intra-oral camera | K40: 1 | L40: RCT | M40: Adults (mean age 38.4, SD 12.49) | N40: 142 | O40: 59 | P40: 38.4 | Q40: No | R40: Yes | S40: 8 months | T40: To determine the effects of intra-oral camera (IOC) during a dental hygiene consultation and mobile text messages (TM) between appointments on clinical, behavioural and psychological parameters of patients with gingivitis, patients were randomly assigned into four conditions: IOC, TM, IOC + TM and control, and examined at three assessment points over eight months. | U40: No | V40: Primary outcomes: frequency of oral hygiene behaviours and decrease in patients’ Bleeding on marginal probing (BOMP). Secondary outcomes: evaluate the effects of these technologies on the psychological determinants described by the HAPA, and to examine the mediating role of these determinants in dental hygiene behaviour and clinical parameters in order to understand how these interventions bring about their effects. | W40: Yes | X40: All treatment groups improved dental hygiene behaviours and revealed a significant decrease in BOMP from baseline to four months, in comparison with the control group. Changes in dental hygiene behaviours proved to be due to changes in flossing rather than in toothbrushing, as modifications for flossing were observed in all groups, but only in the TM group for toothbrushing. Hierarchical linear regressions also showed that individuals in the IOC + TM group had more positive outcome expectancies, revealed higher levels of action self-efficacy and presented a significant improvement in their intention from baseline to four months when compared to the control group. All treatment groups reinforced their maintenance and recovery self-efficacies when compared to the control group from baseline to four months. For action planning, results indicated participants in the TM group lowered their levels of this determinant from baseline to four months. No significant interactions were found for action control or coping planning, even though a main effect for the group was detected for the latter, indicating that individuals in the IOC + TM group had higher levels of coping planning than the control group. Between the four-month and eight-month follow-ups, no differences or slight non-significant decreases in the overall values were detected for almost all the variables. | Y40: Yes | Z40: In person, written communication | AA40: 2 | AB40: Once | AC40: HAPA (Health Action Process Approach) | AD40: Goal directed BCT Increase awareness of consequences BCT Outcome consequence BCT | AE40: 3
A41: Stock ML, Gerrard M, Gibbons FX, Dykstra JL, Mahler HIM, Walsh LA, et al. | B41: Sun Protection Intervention for Highway Workers: Long-Term Efficacy of UV Photography and Skin Cancer Information on Men's Protective Cognitions and Behavior | C41: 2009 | D41: 10.1007/s12160-009-9151-2 | E41: Effective | F41: Sun protection behaviours | G41: 1 | H41: {=_xlfn.TEXTJOIN(", ", TRUE, IF(OR(ISNUMBER(SEARCH({"blood pressure","heart rate","anthropometrics","ecg","vo2max","spirometry","respiratory rate"},I41))),"Physiological", ""), IF(OR(ISNUMBER(SEARCH({"genetic"},I41))),"Risk", ""), IF(OR(ISNUMBER(SEARCH({"ultrasound","uv photog","facial","oral","CT scan"},I41))),"Imaging", ""), IF(OR(ISNUMBER(SEARCH({"glucose","hb1ac","lipids","nutrient"},I41))),"Blood", ""),IF(OR(ISNUMBER(SEARCH({"anthropometrics"},I41))),"Anthropometry", ""))} -> Imaging | I41: UV Photography | J41: Skin colour assessed using skin reflectance spectrophotometry | K41: 1 | L41: Randomised intervention | M41: Male outdoor workers | N41: 148 | O41: 0 | P41: 46.5 | Q41: No | R41: No | S41: 12 months | T41: The overall intervention had two primary elements: (a) a photograph taken of the face with a UV-filter camera and (b) a 12-min educational video on UV risk (focusing on either skin cancer or photoaging). The video discussed the impact of the sun and UV exposure on either photoaging or skin cancer and provided pictures of skin damage (wrinkles and age spots or skin cancer). Each video also provided information about sunscreen use and skin protection (e.g., how much sunscreen to use, an explanation of sun protection factor [SPF], recommendation of an SPF of at least 15). Participants were first randomly assigned by worksite to receive or not receive a UV photo or to be in the control condition. Once the experimenters were at the worksite, they randomly assigned each worker to see the skin cancer or photoaging video. Thus, participants were assigned to one of five conditions: a control condition or one of the four intervention conditions: no-UV/aging, no-UV/skin cancer, UV/aging, UV/skin cancer. All participants first had two Polaroid photos taken of their faces: a natural-light black-and-white photo and a UV photo. The filtered UV light is absorbed by the melanin in the skin and the resulting photo highlights the non-uniform epidermal pigmentation that has resulted from chronic exposure to UV rays. Participants in the control and no-UV photo conditions were only shown the natural-light photo and were told the purpose of this photo would be explained at the end of the study. Men in the UV conditions were shown their natural-light photo and their UV photo as comparison. Participants were told that any “dark, freckled, or splotched areas” in the UV photograph that were not evident in the natural-light photograph indicated existing underlying skin damage due to UV exposure that will get worse if they continue to be exposed to the sun without additional protection. Intervention participants then watched their assigned video (cancer or photoaging). | U41: Yes | V41: Retention of information included in both videos (i.e., minimum recommended SPF level, naming common mistakes people make when using sunscreen), perceptions of skin damage, sun protection attitudes, percieved risk, sun protection behaviours | W41: Yes | X41: When attitudes were assessed, all four intervention conditions were significantly different from the control condition (all Fs > 7.55, ps < 0.01, ds > 0.81). Additional ANCOVAs revealed that none of the intervention conditions was significantly different from all the other intervention conditions (Fs < 0.63, ps > 0.4). When the four intervention conditions were combined, as anticipated, intervention participants reported more positive attitudes toward sun protection than did those in the control condition, F(1, 146) = 11.49, p = 0.001, d = 0.86; Ms = 3.6 vs. 3.1, respectively. When the four intervention conditions were combined, the intervention participants reported more sun protection than did those in the control condition, F(1, 144) = 6.04, p < 0.02, d = 0.68, Ms = 0.78 vs. 1.02, respectively. Participants in the no-UV/aging condition reported marginally higher sun protection than did control participants, F(1, 51) = 3.09, p < 0.09. Participants in the other three intervention conditions reported significantly greater sun protection than those in the control condition (all Fs > 4.15, ps < 0.05, ds ≥ 0.6). Additional ANCOVAs revealed that none of the intervention conditions was significantly different from each other (Fs < 0.82, ps > 0.37). Upon examination of the mean level of sun protection, it was found that the men in the control condition, followed by those in the no-UV/aging condition, had the lowest level of sun protection. Planned comparisons again compared each condition to the control condition. Sun protection in the no-UV/aging condition was not significantly higher than those in the control condition, F(1, 52) = 2.13, p = 0.15. Participants in the other three conditions with the UV photo and/or cancer video had significantly greater sun protection than did those in the control condition (all Fs > 6.95, ps ≤ 0.01, ds > 0.79). Additional ANCOVAs revealed that the men in the other three conditions had significantly higher levels of sun protection at T4, controlling for T1 levels, than did those in the no-UV/aging condition (ps < 0.02). When the three UV and cancer video interventions were combined and compared to the no-UV/aging and control conditions combined, the ANCOVA was also significant, F(1, 146) = 13.66, p < 0.001, d = 0.72. Thus, photoaging information alone did not produce significant changes in long-term sun protection. These results indicate that the most effective interventions for this high-risk male population were those that included the UV photo and/or information related to skin cancer. | Y41: No | Z41: In person, device/online | AA41: 2 | AB41: Once | AC41: Health Belief Model, Prototype Model of Health Behavior | AD41: Increase awareness of consequences BCT | AE41: 1
A42: Mahler, H. I. M., Kulik, J. A., Gerrard, M., & Gibbons, F. X. | B42: Long-Term Effects of Appearance-Based Interventions on Sun Protection Behaviors | C42: 2007 | D42: 10.1037/0278-6133.26.3.350 | E42: Effective | F42: Sun protection behaviours | G42: 1 | H42: {=_xlfn.TEXTJOIN(", ", TRUE, IF(OR(ISNUMBER(SEARCH({"blood pressure","heart rate","anthropometrics","ecg","vo2max","spirometry","respiratory rate"},I42))),"Physiological", ""), IF(OR(ISNUMBER(SEARCH({"genetic"},I42))),"Risk", ""), IF(OR(ISNUMBER(SEARCH({"ultrasound","uv photog","facial","oral","CT scan"},I42))),"Imaging", ""), IF(OR(ISNUMBER(SEARCH({"glucose","hb1ac","lipids","nutrient"},I42))),"Blood", ""),IF(OR(ISNUMBER(SEARCH({"anthropometrics"},I42))),"Anthropometry", ""))} -> Imaging | I42: UV photographs and photoaging information (e.g., wrinkles and age spots) | J42: UV photography and information about photoaging (wrinkles and age spots caused by the sun) | K42: 1 | L42: RCT | M42: Undergraduate students from the University of California (Mean age = 20.13, SD = 3.38) | N42: 133 | O42: 80 | P42: 20.13 | Q42: No | R42: No | S42: 12 months | T42: Participants were randomly assigned to one of four conditions: control, UV photo, photoaging information, or UV photo plus photoaging information. The first follow-up occurred after a period of very high risk for sun exposure, namely, immediately following the summer break (4–5 months after the intervention). A second, final follow-up occurred 1 year after the intervention. Objective assessment of skin color changes (i.e., tanning) was accomplished via skin reflectance spectrophotometry. Of primary interest was whether the two appearance-based interventions (photoaging information and UV photo) would separately increase sun protection intentions and behaviors, and if so, how long any such effects on behavior would last. | U42: No | V42: Participants’ self-reported sun protection intentions assessed immediately after the interventions, and both self-reported sun protection behaviors and an objective assessment (via spectrophotometry) of skin color change measured at the end of summer (4–5 months following interventions) and 1 year following interventions. | W42: Yes | X42: Analyses of the sun protection behavior index indicated that, controlling for a highly significant positive relationship with baseline sun protective behavior, F(1, 78) = 66.06, p < .001, d = 1.84, there was a marginal Video × Time effect, F(1, 79) = 3.12, p = .08, d = 0.40. Analyses of the individual follow-ups indicated that those who had versus those who had not viewed the photoaging video reported significantly more sun protective behavior at the initial postsummer assessment, F(1, 78) = 4.15, p = .045, d = 0.46, but there were no differences at the 1-year follow-up (F < 1, d = 0.00; see Table 3). No effects involving the UV photo condition were significant for this measure. | Y42: No | Z42: In person, device/online | AA42: 2 | AB42: once | AC42: None | AD42: Increase awareness of consequences BCT | AE42: 1
A43: Mahler, H. I. M., Kulik, J. A., Gerrard, M., & Gibbons, F. X. | B43: Effects of Two Appearance-Based Interventions on the Sun Protection Behaviors of Southern California Beach Patrons. | C43: 2006 | D43: 10.1207/s15324834basp2803_5 | E43: Effective | F43: Sun protection behaviours | G43: 1 | H43: {=_xlfn.TEXTJOIN(", ", TRUE, IF(OR(ISNUMBER(SEARCH({"blood pressure","heart rate","anthropometrics","ecg","vo2max","spirometry","respiratory rate"},I43))),"Physiological", ""), IF(OR(ISNUMBER(SEARCH({"genetic"},I43))),"Risk", ""), IF(OR(ISNUMBER(SEARCH({"ultrasound","uv photog","facial","oral","CT scan"},I43))),"Imaging", ""), IF(OR(ISNUMBER(SEARCH({"glucose","hb1ac","lipids","nutrient"},I43))),"Blood", ""),IF(OR(ISNUMBER(SEARCH({"anthropometrics"},I43))),"Anthropometry", ""))} -> Imaging | I43: UV photographs and photoaging information (e.g., wrinkles and age spots) | J43: UV photography and information about photoaging (wrinkles and age spots caused by the sun) | K43: 1 | L43: RCT | M43: Southern California residents (mean age = 35.76, SD = 11.13). | N43: 244 | O43: 59 | P43: 35.76 | Q43: No | R43: No | S43: 8 weeks | T43: Participants were randomly assigned to one of four conditions: control, UV photo, photoaging information, or both UV photo and photoaging information. | U43: No | V43: objective assessment of skin color change (i.e., tanning) via spectrophotometry, sun protection intentions and behaviors. | W43: Yes | X43: A 2 (Photoaging Information) × 2 (UV Photo) ANOVA performed on participants’ future sun protection intentions demonstrated a significant main effect for photoaging information and a marginal main effect for UV photo. Specifically, those who had read the photoaging information 2 months earlier, compared to those who had not, were still reporting significantly stronger intentions to use sun protection at the end of summer, F (1, 216) = 14.00, p < .001. Also, those who had seen their UV photo 2 months earlier were reporting marginally stronger intentions to use sun protection in the future, F (1,216) = 3.16, p < .08. There was also a marginal UV Photo × Photoaging Information interaction, F (1, 216) = 3.70, p < .06. Paired comparisons demonstrated that participants in the control condition (who neither saw their UV photo nor read the photoaging information) expressed significantly lower sun protection intentions at follow-up than did those who received either or both interventions (p < .002, p < .02, p < .002 for comparison with photoaging information only, UV photo only, and combined condition, respectively). Differences between the three intervention conditions were not reliable (all ps > .10). Results demonstrated that reported sun protection during the summer following the intervention was significantly higher for participants’ who also reported greater baseline sun protection use, F (1, 214) = 193.87, p <.001. More importantly, and independent of this relationship, those participants who had received the photoaging information reported greater overall sun protection use, relative to those who had not received the photoaging information, F (1, 214) = 8.16, p < .01. However, this main effect was qualified by a significant UV Photo × Photoaging Information interaction, F (1, 214) = 5.28, p < .05. Follow-up comparisons demonstrated that participants in the control condition reportedly engaged in significantly less sun protection than either those who had seen both the UV photo and the photoaging information (p < .05) or those who had received only the photoaging information (p <.01), and marginally less sun protection than those who had seen only their UV photo (p < .10). In addition, those who received only photoaging information reported marginally more sun protection than those who received only the UV photo (p < .10). No other means differed reliably (p > .10). In accord with those previously noted results, separate regression analyses demonstrated that receiving an intervention, relative to the control condition, resulted in significantly greater immediate sun protection intentions (β coefficient = .59, SEb = .13, p < .001) and greater sun protection behaviors during the subsequent summer months (β coefficient = .20, SEb = .07, p = .002). In addition, when the sun protection behavior was simultaneously regressed on intervention condition and sun protection intentions, participants’ immediate intentions significantly predicted later sun protection behaviors (β coefficient = .22, SEb= .04, p < .001) while reducing the intervention effect on sun protection behavior to nonsignificance (β coefficient = .06, SEb = .07, p > .35). | Y43: No | Z43: In person, device/online | AA43: 2 | AB43: once | AC43: Health Belief Model, Protection Motivation Theory, Theory of Planned Behavior | AD43: Increase awareness of consequences BCT Increase awareness of behaviour BCT | AE43: 2
A44: Gibbons, F. X., Gerrard, M., Lane, D. J., Mahler, H. I. M., & Kulik, J. A. | B44: Using UV Photography to Reduce Use of Tanning Booths: A Test of Cognitive Mediation. | C44: 2005 | D44: 10.1037/0278-6133.24.4.358 | E44: Effective | F44: Tanning-booth use | G44: 1 | H44: {=_xlfn.TEXTJOIN(", ", TRUE, IF(OR(ISNUMBER(SEARCH({"blood pressure","heart rate","anthropometrics","ecg","vo2max","spirometry","respiratory rate"},I44))),"Physiological", ""), IF(OR(ISNUMBER(SEARCH({"genetic"},I44))),"Risk", ""), IF(OR(ISNUMBER(SEARCH({"ultrasound","uv photog","facial","oral","CT scan"},I44))),"Imaging", ""), IF(OR(ISNUMBER(SEARCH({"glucose","hb1ac","lipids","nutrient"},I44))),"Blood", ""),IF(OR(ISNUMBER(SEARCH({"anthropometrics"},I44))),"Anthropometry", ""))} -> Imaging | I44: UV photographs and photoaging information (e.g., wrinkles and age spots) | J44: UV photographs and photoaging information (e.g., wrinkles and age spots) | K44: 1 | L44: RCT | M44: Undergraduates randomly selected from a list of students enrolled in introductory psychology classes. As exact ages were not reported, we inferred the "mean age" as the median age of all college-attending students in the US in 2005. | N44: 70 | O44: 51 | P44: 23 | Q44: No | R44: No | S44: 1 month | T44: An appearance-based intervention that uses a camera with a UV filter. The camera produces a photo that reveals the normally invisible damage caused by UV exposure. Chronic exposure accelerates photoaging and produces nonuniform epidermal pigmentation, which appears in the photo as dark blotches that are quite prominent and impactful. Two studies were conducted as follow-ups and extensions to the study by Mahler et al., using a different set of mediators and a different type of UV exposure. Upon arrival at the lab, participants were randomly assigned to either a UV photo or no-UV-photo (NUV) condition. Experimenters showed UV students both pictures, pointing out the dark-splotch areas of excessive exposure (damage) in the UV photo and stating that the splotches indicated damage from UV exposure that had already been incurred. More than 90% of students had some visible damage. UV students also received a 2-min oral presentation about UV exposure in which it was explained that (a) UV exposure leads to premature skin wrinkling (photoaging) and increases risk for skin cancer, (b) skin cancer and photoaging have increased in the United States recently, and (c) most skin damage occurs before adulthood, so the college years are crucial for sun protection. NUV condition participants waited for the 2-min period. All participants then completed the primary questionnaire. Finally, there was an extensive debriefing for all students, which included information from the 2-min oral presentation. Also, all participants were given three brochures that described photoaging and melanoma and listed common sun protection methods (e.g., using sunscreen with a sun protection factor greater than 15). Thus, by the end of the study, risk information provided to the two groups was almost identical. After receiving or not receiving a copy of their UV photograph, students responded to a questionnaire that contained measures of tanning attitudes and cognitions suggested by the prototype model. They returned approximately 4 weeks later and again responded to the questionnaire and reported on their booth use since the first session. The design of Study 2 was similar to that of Study 1 except that the differences between the UV and NUV conditions were minimized—that is, the same information about UV risk was presented in both conditions and all students (not just those in the UV condition) received a natural-light photo of their faces. Also, the wording of some of the questions was changed slightly. | U44: Yes | V44: Several attitude measures were taken: attitudes, prototypes, willingness, and perceived vulnerability (PV) to photoaging. Sun-protection behaviours were also measured. | W44: No | X44: The percentage of students in the NUV condition reporting booth use increased noticeably after the experimental session (from 28% to 47%). An increase this time of year (April) is not surprising. In the UV condition, however, reported use declined (from 31% to 16%), suggesting that the photo cut use by more than two thirds. This change in behavior was partially (but significantly) mediated by the cognitions that were assessed, all of which were affected by the camera. | Y44: No | Z44: In person, written communication | AA44: 2 | AB44: once | AC44: None | AD44: Increase awareness of consequences BCT Increase awareness of behaviour BCT | AE44: 2
A45: Araújo M-R, Alvarez M-J, Godinho CA, Pereira C | B45: Psychological, behavioral, and clinical effects of intra-oral camera: a randomized control trial on adults with gingivitis | C45: 2016 | D45: 10.1111/cdoe.12245 | E45: Effective | F45: Oral health behaviour | G45: 1 | H45: {=_xlfn.TEXTJOIN(", ", TRUE, IF(OR(ISNUMBER(SEARCH({"blood pressure","heart rate","anthropometrics","ecg","vo2max","spirometry","respiratory rate"},I45))),"Physiological", ""), IF(OR(ISNUMBER(SEARCH({"genetic"},I45))),"Risk", ""), IF(OR(ISNUMBER(SEARCH({"ultrasound","uv photog","facial","oral","CT scan"},I45))),"Imaging", ""), IF(OR(ISNUMBER(SEARCH({"glucose","hb1ac","lipids","nutrient"},I45))),"Blood", ""),IF(OR(ISNUMBER(SEARCH({"anthropometrics"},I45))),"Anthropometry", ""))} -> Imaging | I45: Imaging oral health | J45: Intra-oral camera | K45: 1 | L45: RCT | M45: Adults. As ages are bucketed, mean ages of buckets are used (e.g., "25-34 years" = 29.5 years). Age of the single participant in the ">75 years" group is assumed to be 75. | N45: 78 | O45: 56.25 | P45: =(21*(9+5)+29.5*(11+10)+39.5*(9+11)+49.5*(8+8)+65*(2+5)+75*(1+1))/(40+40) -> 38.75625 | Q45: No | R45: Yes | S45: 4 months | T45: To evaluate the effects of using an intra-oral camera (IOC) during supportive periodontal therapy (SPT), participants were randomised into two groups: IOC and control. The dental consultation, which was the same for both groups, was performed by the experienced dental hygienist, lasted 1 h and included activities that are normally part of supportive periodontal therapy (SPT). It also included specific behavior change techniques, such as reinforcement (10.4), goal-setting (1.1), and feedback (2.2, 2.7). The control group was also an active group with a communication pathway based on these strategies. | U45: Yes | V45: Primary outcome: increasing gingival health verified by the Bleeding on Marginal Probing (BOMP). Secondary outcomes included effects on the self-reported frequency of dental hygiene behaviors and their relevant psychological determinants. | W45: No | X45: A main effect of time was revealed for dental hygiene and for flossing, indicating an increase across the two periods of time (Table 1). This increase was reliable in the IOC group both for dental hygiene, F(1,76) = 53.58, P < 0.001, η2 = 0.41, and flossing F(1,76) = 73.17, P < 0.001, η2 = 0.49. The same trend was observed in the control group for dental hygiene, F(1,76) = 15.96, P < 0.001, η2 = 0.17, and for flossing, F(1,76) = 25.71, P < 0.001, η2 = 0.25. Importantly, an interaction between group and time emerged for dental hygiene and for flossing, neither of which showed any differences between the groups at baseline: Fdental hygiene (1,76) = 0.11, ns, η2 = 0.00; flossing (1,76) = 0.83, ns, η2 = 0.01 (Fig. 2). An increase in dental hygiene and flossing in both groups at 4 months was observed (Table 1), which was higher in the IOC group than in the control condition: Fdental hygiene (1,76) = 4.68, P < 0.05, η2 = 0.06; Fflossing (1,76) = 4.29, P < 0.05, η2 = 0.05. | Y45: No | Z45: In person | AA45: 1 | AB45: Once | AC45: Health Action Process Approach (HAPA) | AD45: Goal directed BCT Increase awareness of consequences BCT Increase awareness of behaviour BCT | AE45: 3
A46: Gibbons, F. X., Gerrard, M., Lane, D. J., Mahler, H. I. M., & Kulik, J. A. | B46: Using UV Photography to Reduce Use of Tanning Booths: A Test of Cognitive Mediation. | C46: 2005 | D46: 10.1037/0278-6133.24.4.358 | E46: Effective | F46: Tanning-booth use | G46: 1 | H46: {=_xlfn.TEXTJOIN(", ", TRUE, IF(OR(ISNUMBER(SEARCH({"blood pressure","heart rate","anthropometrics","ecg","vo2max","spirometry","respiratory rate"},I46))),"Physiological", ""), IF(OR(ISNUMBER(SEARCH({"genetic"},I46))),"Risk", ""), IF(OR(ISNUMBER(SEARCH({"ultrasound","uv photog","facial","oral","CT scan"},I46))),"Imaging", ""), IF(OR(ISNUMBER(SEARCH({"glucose","hb1ac","lipids","nutrient"},I46))),"Blood", ""),IF(OR(ISNUMBER(SEARCH({"anthropometrics"},I46))),"Anthropometry", ""))} -> Imaging | I46: UV photographs and photoaging information (e.g., wrinkles and age spots) | J46: UV photographs and photoaging information (e.g., wrinkles and age spots) | K46: 1 | L46: RCT | M46: College students. As exact ages were not reported, we inferred the "mean age" as the median age of all college-attending students in the US in 2005. | N46: 134 | O46: 53.7 | P46: 23 | Q46: No | R46: No | S46: 1 month | T46: An appearance-based intervention that uses a camera with a UV filter. The camera produces a photo that reveals the normally invisible damage caused by UV exposure. Chronic exposure accelerates photoaging and produces nonuniform epidermal pigmentation, which appears in the photo as dark blotches that are quite prominent and impactful. Two studies were conducted as follow-ups and extensions to the study by Mahler et al., using a different set of mediators and a different type of UV exposure. Upon arrival at the lab, participants were randomly assigned to either a UV photo or no-UV-photo (NUV) condition. Experimenters showed UV students both pictures, pointing out the dark-splotch areas of excessive exposure (damage) in the UV photo and stating that the splotches indicated damage from UV exposure that had already been incurred. More than 90% of students had some visible damage. UV students also received a 2-min oral presentation about UV exposure in which it was explained that (a) UV exposure leads to premature skin wrinkling (photoaging) and increases risk for skin cancer, (b) skin cancer and photoaging have increased in the United States recently, and (c) most skin damage occurs before adulthood, so the college years are crucial for sun protection. NUV condition participants waited for the 2-min period. All participants then completed the primary questionnaire. Finally, there was an extensive debriefing for all students, which included information from the 2-min oral presentation. Also, all participants were given three brochures that described photoaging and melanoma and listed common sun protection methods (e.g., using sunscreen with a sun protection factor greater than 15). Thus, by the end of the study, risk information provided to the two groups was almost identical. After receiving or not receiving a copy of their UV photograph, students responded to a questionnaire that contained measures of tanning attitudes and cognitions suggested by the prototype model. They returned approximately 4 weeks later and again responded to the questionnaire and reported on their booth use since the first session. The design of Study 2 was similar to that of Study 1 except that the differences between the UV and NUV conditions were minimized—that is, the same information about UV risk was presented in both conditions and all students (not just those in the UV condition) received a natural-light photo of their faces. Also, the wording of some of the questions was changed slightly. | U46: Yes | V46: Several attitude measures were taken: attitudes, prototypes, willingness, and perceived vulnerability (PV) to photoaging. Sun-protection behaviours were also measured. | W46: No | X46: Baseline reports of prior booth use did not differ across conditions in terms of percentage using (UV = 47%, NUV = 44%) or amount of reported use (p =.20). At T2, the percentage figures were as follows: UV = 27%, NUV = 39%. A logistic regression of T2 use reports, controlling for T1 use, revealed a strong effect of previous use (Wald = 20.75, p <.001) and a marginal effect of condition (Wald = 3.06, p <.08, odds ratio = 2.36). Hierarchical regressions on amount of use at T2 indicated that previous use (β =.45), t(106) = 5.31, and UV condition (β = −.23), t(106) = −2.72, were both significant predictors (both ps <.008); thus, viewing the photos was again associated with significantly less T2 booth use. | Y46: No | Z46: In person, written communication | AA46: 2 | AB46: once | AC46: None | AD46: Increase awareness of consequences BCT Increase awareness of behaviour BCT | AE46: 2
A47: Mahler, H. I. M., Kulik, J. A., Gibbons, F. X., Gerrard, M., & Harrell, J. | B47: Effects of appearance-based intervention on sun protection intentions and self-reported behaviors | C47: 2003 | D47: 10.1037/0278-6133.22.2.199 | E47: Effective | F47: Sun protection behaviours | G47: 1 | H47: {=_xlfn.TEXTJOIN(", ", TRUE, IF(OR(ISNUMBER(SEARCH({"blood pressure","heart rate","anthropometrics","ecg","vo2max","spirometry","respiratory rate"},I47))),"Physiological", ""), IF(OR(ISNUMBER(SEARCH({"genetic"},I47))),"Risk", ""), IF(OR(ISNUMBER(SEARCH({"ultrasound","uv photog","facial","oral","CT scan"},I47))),"Imaging", ""), IF(OR(ISNUMBER(SEARCH({"glucose","hb1ac","lipids","nutrient"},I47))),"Blood", ""),IF(OR(ISNUMBER(SEARCH({"anthropometrics"},I47))),"Anthropometry", ""))} -> Imaging | I47: UV Photography | J47: UV photography and information about photoaging (wrinkles and age spots caused by the sun) | K47: 1 | L47: RCT | M47: Southern California residents (mean age = 35.28,SD = 9.89) | N47: 76 | O47: 65.7 | P47: 35.28 | Q47: No | R47: No | S47: 1 month | T47: Participants from both experiments were randomly assigned to receive or not receive a photoaging (premature wrinkling and age spots) information intervention and, separately, to receive or not receive a novel ultraviolet (UV) photo intervention that makes the negative-appearance consequences of UV exposure more salient. Photoaging information was delivered via a 12-min videotaped slide show which depicted photoaging (including very graphic photos of extreme cases of wrinkles and age spots), described how sun exposure and UV radiation from any source leads to photoaging, and discussed effective practices for minimizing photoaging (e.g., wearing protective clothing and applying a broad spectrum sunscreen that protects against UVB and UVA rays with an SPF of at least 15). The video also provided general information about sunscreen, such as what thesun protection factor (SPF) means, how much sunscreen to apply, and when to use sunscreen. UV facial photographs were taken with a modified instant Polaroid camera that has a special UV filter. Filtered UV light is absorbed by the melanin in the skin. The resulting black-and-white UV photograph highlights, quite clearly and dramatically, the nonuniform epidermal pigmentation that results from chronic sun exposure. Each person who had a UV photo taken also had a natural light instant photograph taken for comparison. In all cases, the natural light black-and-white photograph was shown to participants first, followed by the UV photograph. Participants were told that any “dark, freckled, or pitted areas” in the UV photo (that did not appear in the natural light photo) indicate existing underlying skin damage that would continue to get worse if participants did not engage in sun protection behaviors. | U47: Yes | V47: Changes to sun protection intentions and behaviours | W47: Yes | X47: Beach participants who saw a UV photo of their face, compared with those who did not, reported stronger intentions to use sunscreen regularly in the future,F(1, 70) = 5.47,p <.03. Separate analyses that were performed on the measures of perceived rewards of tanning, perceived costs of using sunscreen, perceived severity of photoaging, perceived susceptibility to photoaging, and perceived efficacy of sunscreen for protection against photoaging generally revealed no reliable effects of either the UV photo or the photoaging interventions. | Y47: No | Z47: In person, written communication | AA47: 2 | AB47: Once | AC47: None | AD47: Increase awareness of consequences BCT | AE47: 1
A48: Mahler, H. I. M., Kulik, J. A., Gibbons, F. X., Gerrard, M., & Harrell, J. | B48: Effects of appearance-based intervention on sun protection intentions and self-reported behaviors | C48: 2003 | D48: 10.1037/0278-6133.22.2.199 | E48: Not effective | F48: Sun protection behaviours | G48: 1 | H48: {=_xlfn.TEXTJOIN(", ", TRUE, IF(OR(ISNUMBER(SEARCH({"blood pressure","heart rate","anthropometrics","ecg","vo2max","spirometry","respiratory rate"},I48))),"Physiological", ""), IF(OR(ISNUMBER(SEARCH({"genetic"},I48))),"Risk", ""), IF(OR(ISNUMBER(SEARCH({"ultrasound","uv photog","facial","oral","CT scan"},I48))),"Imaging", ""), IF(OR(ISNUMBER(SEARCH({"glucose","hb1ac","lipids","nutrient"},I48))),"Blood", ""),IF(OR(ISNUMBER(SEARCH({"anthropometrics"},I48))),"Anthropometry", ""))} -> Imaging | I48: UV Photography | J48: UV photography and information about photoaging (wrinkles and age spots caused by the sun) | K48: 1 | L48: RCT | M48: Undergraduates from the University of California (mean age 20.13,SD = 2.55). | N48: 68 | O48: 86.7 | P48: 20.13 | Q48: No | R48: No | S48: 1 month | T48: Participants from both experiments were randomly assigned to receive or not receive a photoaging (premature wrinkling and age spots) information intervention and, separately, to receive or not receive a novel ultraviolet (UV) photo intervention that makes the negative-appearance consequences of UV exposure more salient. Photoaging information was delivered via a 12-min videotaped slide show which depicted photoaging (including very graphic photos of extreme cases of wrinkles and age spots), described how sun exposure and UV radiation from any source leads to photoaging, and discussed effective practices for minimizing photoaging (e.g., wearing protective clothing and applying a broad spectrum sunscreen that protects against UVB and UVA rays with an SPF of at least 15). The video also provided general information about sunscreen, such as what thesun protection factor (SPF) means, how much sunscreen to apply, and when to use sunscreen. UV facial photographs were taken with a modified instant Polaroid camera that has a special UV filter. Filtered UV light is absorbed by the melanin in the skin. The resulting black-and-white UV photograph highlights, quite clearly and dramatically, the nonuniform epidermal pigmentation that results from chronic sun exposure. Each person who had a UV photo taken also had a natural light instant photograph taken for comparison. In all cases, the natural light black-and-white photograph was shown to participants first, followed by the UV photograph. Participants were told that any “dark, freckled, or pitted areas” in the UV photo (that did not appear in the natural light photo) indicate existing underlying skin damage that would continue to get worse if participants did not engage in sun protection behaviors. | U48: Yes | V48: Changes to sun protection intentions and behaviours | W48: Yes | X48: A 2 (photoaging information) × 2 (UV photo) analysis of covariance (ANCOVA), with skin type and amount of sunbathing in the prior 2 weeks entered as covariates, indicated some tendency for participants with more sun-reactive skin to express greater intentions to use sunscreen (p <.10) but no independent relationship of sunbathing levels in the prior 2 weeks with intentions (p >.17). Those in the UV photo condition compared with those in the no UV photo condition had significantly stronger intentions to use sunscreen regularly in the future,F(1, 62) = 15.82,p <.001. Participants who watched the photoaging video perceived photoaging to be a more severe condition,F(1, 64) = 3.92,p =.05, and were more convinced of the efficacy of sunscreen use for the prevention of photoaging,F(1, 64) = 4.84,p =.03, but they did not express greater self-efficacy beliefs for regular sunscreen use (p >.20). Photoaging information also did not significantly influence perceptions of the rewards of tanning, costs of using sun protection, or susceptibility to photoaging (Fs < 1.04). None of these analyses produced evidence of UV Photo × Photoaging Information effects (allps >.25). participants' perceptions of self-efficacy for using sunscreen and perceptions of the rewards of tanning each predicted intentions (p <.001 for self-efficacy,p <.04 for rewards of tanning) while reducing the UV photo effect on intentions. However, in neither case was the reduction of the UV photo effect significant). Thus, we found no compelling evidence that these perceptions mediated the effect of the UV photo on intentions to use sunscreen in the future. | Y48: No | Z48: In person, written communication | AA48: 2 | AB48: Once | AC48: None | AD48: Increase awareness of consequences BCT | AE48: 1
A49: Lederman J, Ballard J, Njike VY, Margolies L, Katz DL. | B49: Information given to postmenopausal women on coronary computed tomography may influence cardiac risk reduction efforts | C49: 2007 | D49: 10.1016/j.jclinepi.2006.07.010 | E49: Not effective | F49: Diet, physical activity, medication changes, smoking cessation | G49: 4 | H49: {=_xlfn.TEXTJOIN(", ", TRUE, IF(OR(ISNUMBER(SEARCH({"blood pressure","heart rate","anthropometrics","ecg","vo2max","spirometry","respiratory rate"},I49))),"Physiological", ""), IF(OR(ISNUMBER(SEARCH({"genetic"},I49))),"Risk", ""), IF(OR(ISNUMBER(SEARCH({"ultrasound","uv photog","facial","oral","CT scan"},I49))),"Imaging", ""), IF(OR(ISNUMBER(SEARCH({"glucose","hb1ac","lipids","nutrient"},I49))),"Blood", ""),IF(OR(ISNUMBER(SEARCH({"anthropometrics"},I49))),"Anthropometry", ""))} -> Imaging | I49: DHCT scan | J49: Cardiac screening with double-helical computed tomography (DHCT) scan | K49: 1 | L49: randomised, prospective trial | M49: Post-menopausal women (mean age of intervention group was 63.8 ± 7.0 years old, and the conventional screening group was 65.5 ± 6.8 years old) | N49: 56 | O49: 100 | P49: =(63.8*26+65.5*30)/(26+30) -> 64.710714 | Q49: Yes | R49: Yes | S49: 12 months | T49: This study compared conventional cardiac risk factor screening with conventional screening plus coronary DHCT to determine their impact on behavioral risk factors in postmenopausal women. One week after the conventional screening and baseline questionnaire assessment, all subjects returned for a scripted counselling session performed by a preventive medicine resident. Based on the results of conventional screening, performed at the baseline visit, all subjects received a tailored counselling session from a preventive medicine resident physician regarding nutrition, supplement use, physical activity, weight management, smoking cessation, and appropriate use of HRT and pharmacotherapy for CHD risk reduction. This session occurred within 1 week of their conventional screening assessment. All study participants received this counselling session regardless of their assignment to DHCT or control. After the counselling session, the subjects were randomised. Subjects in the DHCT group were shown images of their coronary arteries and received an interpretation from a Griffin Hospital staff radiologist involved in the study. Based on the coronary calcification score, subjects were categorized into four risk categories (minimal/zone, mild, moderate or severe). Tthe results of the DHCT were provided to their GP, alongside recommendations to improve each patient's cardiac risk profile. | U49: Yes | V49: Primary outcomes: change in blood pressure, change in glucose level, change in BMI, change in the lipid profile, and change in the coronary calcification score. Additional oucomes: change in dietary fat, fiber, and micronutrient intake; change in PA level; change in the subject's use of HRT and change in the subject's smoking status. | W49: No | X49: The proportion of participants who increased blood pressure medication use, cholesterol medication use, and fiber intake, and reduced fat intake did not differ between treatment groups. However, the proportion of participants who increased blood pressure medication use in the conventionally screened group (13.3%) was almost twice that of the DHCT group (7.7%). The proportion of participants who increased cholesterol medication use in the conventionally screened group (20.0%) was approximately three times more than that in the DHCT group (7.7%). The percentage of subjects who increased fiber intake in the control group (28.6%) was more than two times that of the DHCT group (13.0%). The fraction of participants who decreased fat intake was more in the DHCT group (29.2%) compared to that of the conventional group (17.9%). At 6 months of follow-up, biomarker improvements measures did not differ significantly (P > 0.05) between treatment groups. Outcome measures did not improve significantly (P > 0.05) from baseline values in the DHCT group. In the conventional group, systolic blood pressure, total cholesterol, and low-density lipoprotein improved significantly (P < 0.05) from their baseline values. The improvement observed at 12 months of follow-up from baseline differed significantly (P > 0.05) between treatment groups in total cholesterol (DHCT = −3.35 ± 26.56; conventional = −20.27 ± 34.89: P-value <0.05), LDL (DHCT = 1.15 ± 26.80; conventional = −17.43 ± 29.18: P-value <0.05), and cholesterol/HDL (DHCT = 0.18 ± 0.57; conventional = −0.48 ± 0.87: P-value <0.05). All outcome measures improved nonsignificantly (P > 0.05) from baseline values in the DHCT group. In the conventionally screened group, total cholesterol, LDL, and total cholesterol to HDL ratio improved significantly (P < 0.05) from their baseline values. | Y49: No | Z49: In person, written communication | AA49: 2 | AB49: Once | AC49: None | AD49: Social support BCT Increase awareness of consequences BCT Outcome consequence BCT | AE49: 3
A50: Harris, R., Lowers, V., Laverty, L. et al. | B50: Comparing how patients value and respond to information on risk given in three different forms during dental check-ups: the PREFER randomised controlled trial. | C50: 2020 | D50: 10.1186/s13063-019-3824-3 | E50: Not effective | F50: Oral health behaviour | G50: 1 | H50: {=_xlfn.TEXTJOIN(", ", TRUE, IF(OR(ISNUMBER(SEARCH({"blood pressure","heart rate","anthropometrics","ecg","vo2max","spirometry","respiratory rate"},I50))),"Physiological", ""), IF(OR(ISNUMBER(SEARCH({"genetic"},I50))),"Risk", ""), IF(OR(ISNUMBER(SEARCH({"ultrasound","uv photog","facial","oral","CT scan"},I50))),"Imaging", ""), IF(OR(ISNUMBER(SEARCH({"glucose","hb1ac","lipids","nutrient"},I50))),"Blood", ""),IF(OR(ISNUMBER(SEARCH({"anthropometrics"},I50))),"Anthropometry", ""))} -> Imaging | I50: Imaging oral health | J50: Quantitative light fluorescence (QLF) photograph of the patient’s mouth | K50: 1 | L50: RCT | M50: Adults at medium/high risk of poor oral health. Ages are reported in buckets--for overall mean age estimation, mean age of buckets are used (e.g., "18-34 years old" = 26 years old); mean age of the "65+ years" is approximated to 70. | N50: 412 | O50: 60 | P50: =(26*43+49.5*77+70*32)/183 -> 39.177596 | Q50: Yes | R50: Yes | S50: 12 months | T50: After receiving their check-up, patients were randomised to recieve different oral health risk information (verbal advice (V) compared to verbal advice accompanied by a traffic light (TL) risk card; or compared to verbal advice with a quantitative light fluorescence (QLF) photograph of the patient’s mouth). In the TL arm, dentists gave patients either small Red or Amber risk cards which had a message on the reverse about how to reduce their oral health risk. This was explained by the dentist, who ticked the boxes which were most relevant to that patient. In the QLF arm, patients were shown a QLF photograph of their anterior teeth and received a copy printed as a credit card, the back of which again contained messages about how to reduce their risk. Dentists explained the photograph to patients – explaining any dark (demineralised) or red (mature plaque) areas on the picture. Dentists gave usual care (V) with a card containing the checked list of any messages covered. Follow-up was by telephone/e-mail at 6 and 12 months. | U50: Yes | V50: The primary outcome was willingness to pay (WTP). Secondary outcomes included self-rated oral health and change in oral health behaviours (tooth-brushing, sugar consumption and smoking). | W50: No | X50: Using multivariate generalised linear mixed models, no significant effect in oral health behaviours (smoking; brushing frequency; brushing duration; sugar in food; sugar in drinks; sugar added to drinks) was found for any of the information arms between baseline and 6-month follow-up (F = 0.84, p = 0.432) or between baseline and 12 months (F = 1.90, p = 0.150). Analysis using MANCOVAs to test whether there were information-type intervention interaction effects with potential moderators (gender, age, income, education, IMD number of teeth, dental attendance and practice attended) showed none, at either 6-month or 12-month follow-up. | Y50: No | Z50: In person, written communication | AA50: 2 | AB50: Once | AC50: None | AD50: Increase awareness of consequences BCT Outcome consequence BCT | AE50: 2
A52: Papers from reviews cited in French et al., 2017 DOI:10.1007/s12160-017-9895-z, Table 1 (https://academic.oup.com/view-large/105254636)
A53: USHER-SMITH ET AL. | B53: 10.1136/bmjopen-2015-008717
A54: Price, H.C., Griffin, S.J. and Holman, R.R. | B54: Impact of personalized cardiovascular disease risk estimates on physical activity—a randomized controlled trial. | C54: 2011 | D54: 10.1111/j.1464-5491.2010.03212.x | E54: Not effective | F54: Physical activity | G54: 1 | H54: {=_xlfn.TEXTJOIN(", ", TRUE, IF(OR(ISNUMBER(SEARCH({"blood pressure","heart rate","anthropometrics","ecg","vo2max","spirometry","respiratory rate"},I54))),"Physiological", ""), IF(OR(ISNUMBER(SEARCH({"genetic"},I54))),"Risk", ""), IF(OR(ISNUMBER(SEARCH({"ultrasound","uv photog","facial","oral","CT scan"},I54))),"Imaging", ""), IF(OR(ISNUMBER(SEARCH({"glucose","hb1ac","lipids","nutrient"},I54))),"Blood", ""),IF(OR(ISNUMBER(SEARCH({"anthropometrics"},I54))),"Anthropometry", ""))} -> Physiological, Blood | I54: Blood pressure, lipids, glucose, HbA1c | J54: Blood pressure, LDL cholesterol, HbA1c, fasting blood glucose | K54: 4 | L54: RCT | M54: Adults (19% having known diabetes). | N54: 194 | O54: 33 | P54: 62.3 | Q54: No | R54: No | S54: 1 month | T54: Participants were randomised to receive a personalized 10-year cardiovascular disease risk estimate (N=99) or to receive the control intervention (N=95). Participants randomized to receive a risk estimate had their 10-year cardiovascular disease and fatal cardiovascular disease risks estimated using the UK Prospective Diabetes Study Risk Engine. An interface was developed for this risk calculator with the aim of achieving maximal comprehension by participants. This displayed current risk and also ‘achievable risk’. Achievable risk was the risk estimate calculated assuming current targets for systolic blood pressure, LDL cholesterol, HbA1c and smoking cessation (if applicable) were met. A printout of current and achievable risk was provided to participants randomized to receive a personalized 10-year risk estimate at the time the intervention was delivered. General practitioners were only provided with risk estimates once a participant had completed the study. The control group were told their fasting glucose level, blood pressure and LDL cholesterol and informed if they were elevated according to current guidelines. A written record of these results was also provided. Next, both the risk estimate and control groups were randomised into two groups, half receiving a brief lifestyle advice intervention. The half not randomized to receive the brief lifestyle advice intervention received no intervention and no written materials. The brief lifestyle advice intervention was a computerized slide show, which participants worked through themselves and that aimed to motivate behaviour changes designed to reduce cardiovascular disease risk through the setting of goals and the steering of behaviour towards their achievement. Goal setting was encouraged to fit in with other factors in participants’ lives, including family and financial constraints. Whilst the slides encouraged participants to consider barriers to achieving lifestyle change and to set their own goals, these were not discussed with the investigators. It took approximately 15 min for each participant to work through the presentation. The intervention stressed that even small changes in behaviour were beneficial to health and focused on increasing physical activity, fruit and vegetable consumption, decreasing alcohol intake and smoking cessation if necessary. The physical activity goal was 30 min of brisk walking per day in line with current guidelines and the fruit and vegetable goal was five portions per day. A reduction in alcohol consumption was advised if current intake was above UK government recommendations (not more than 3–4 units per day for men and 2–3 units per day for women). At the end of the computer presentation, participants were given a leaflet repeating the advice they had been given. | U54: No | V54: Primary outcome: Physical activity. Secondary outcomes: anthropometric and biochemical measurements. Tertiary outcomes: impact of the intervention on anxiety, quality of life, self-regulation, worry about future risk of heart attacks, intention to increase physical activity and recall of risk information given. | W54: Yes | X54: 53% of participants increased their physical activity by 30×10−3 total counts per day overall. Non-significant net 0.5% (95% CI −0.6–1.8%) (8×10−3 total counts per day) (P=0.56) greater increase in accelerometer counts in those receiving personalized cardiovascular disease risk estimates. No significant within- or between-group differences were seen in weight, blood pressure, HDL cholesterol, triglycerides, estimated 10-year cardiovascular disease risk, plasma vitamin C or serum cotinine in smokers. | Y54: No | Z54: Device/Online, Written information | AA54: 2 | AB54: Once | AC54: Self-regulation theory | AD54: Increase awareness of consequences BCT Goal directed BCT Outcome consequence BCT | AE54: 3
A55: SHERIDAN ET AL. | B55: 10.1001/archinternmed.2009.516
A56: Williams GC, McGregor H, Sharp D, Kouldes RW, Lévesque CS, Ryan RM, Deci EL | B56: A self-determination multiple risk intervention trial to improve smokers' health | C56: 2006 | D56: 10.1111/j.1525-1497.2006.00621.x | E56: Effective | F56: Diet, smoking cessation | G56: 2 | H56: {=_xlfn.TEXTJOIN(", ", TRUE, IF(OR(ISNUMBER(SEARCH({"blood pressure","heart rate","anthropometrics","ecg","vo2max","spirometry","respiratory rate"},I56))),"Physiological", ""), IF(OR(ISNUMBER(SEARCH({"genetic"},I56))),"Risk", ""), IF(OR(ISNUMBER(SEARCH({"ultrasound","uv photog","facial","oral","CT scan"},I56))),"Imaging", ""), IF(OR(ISNUMBER(SEARCH({"glucose","hb1ac","lipids","nutrient"},I56))),"Blood", ""),IF(OR(ISNUMBER(SEARCH({"anthropometrics"},I56))),"Anthropometry", ""))} -> Physiological, Blood | I56: Blood lipids, blood pressure | J56: LDL-C, BP | K56: 2 | M56: Adult smokers | N56: 1006 | O56: 63.9 | P56: 45.5 | Q56: No | R56: No | S56: 12 months | T56: Patients were randomly assigned to community care (CC, 30%) and intensive tobacco treatment (70%). The randomisation was stratified by whether a dietary intervention was indicated based on the National Cholesterol Education Program's (NCEP's) LDL-C goals. 20 Patients who were at LDL-C goal were randomized to tobacco intervention or CC. Patients not at LDL-C goal were randomized to (1) tobacco and dietary intervention, (2) tobacco intervention and dietary CC, or (3) community care for both tobacco and diet. The intervention groups recieved a 6-month clinical intervention (4 contacts) to facilitate internalisation of autonomy and perceived competence for tobacco abstinence and reduced percent calories from fat was compared with community care. Clinicians elicited patient perspectives and goals, provided absolute coronary artery disease risk estimates, advised on effective treatment options, supported patient initiatives, supported patient autonomy, assessed motivation for change, and developed a plan for change. Patients randomized to CC completed questionnaires and then received the National Cancer Institute booklet “You Can Quit Smoking,” a copy of their cholesterol test results, the American Dietetic Association booklet on elevated cholesterol “The New Cholesterol Countdown,” and a list of active area smoking cessation programs. They were encouraged to enroll in a cessation program and to meet with their physician. | U56: Yes | V56: Twelve-month prolonged tobacco abstinence, and change in percent calories from fat and low-density lipoprotein-cholesterol (LDL-C) from baseline to 18 months. | W56: Yes | X56: The primary outcome of 12-month prolonged abstinence was significantly higher in the intervention condition (6.2% vs 2.4%, P=.01, Number Needed to Treat [NNT]=26.3). The mean days since last cigarette (37.30 vs 17.58, P=.01) and the longest time not smoking (59.05 vs 28.88 days, P<.001) were greater for the intervention group. The intensive treatment patients perceived greater autonomy support at 1 month (P<.001 by t-test), and internalized greater autonomous motivation for cessation (P<.05 by ANCOVA), for taking medications (P=.001), and greater perceived competence (P<.001) from baseline to 6 months. Abstinence rates were the same for the smoking intervention alone compared with the smoking and diet intervention, so all smoking intervention patients were analyzed together. In addition to group assignment, 12-month abstinence was significantly predicted by: 1-month autonomy support (odds ratio [OR]=1.69; 95% confidence interval [CI]: 1.15, 2.49), change in autonomous motivation for cessation (OR=1.65; 95% CI: 1.05, 2.58), change in perceived competence (OR=2.89; 95% CI: 2.13, 3.93), and the days of medication use in 6 months (OR=1.01; 95% CI: 1.010, 1.012). Change in autonomous motivation for taking medications from baseline to 1 month predicted 12-month abstinence (OR=1.39; 95% CI: 1.07, 1.82), but change to 6 months did not. There was no difference in change in percent calories from fat from baseline to 18 months between the groups (+0.92% vs +0.17%, P=.39). However, reduction in LDL-C from baseline to 18 months was significantly greater in the intervention compared with CC group (–8.9 vs –4.1 mg/dL; P=.05). There was no effect of the diet intervention on the motivation variables, and thus the intervention and CC groups were combined for further analyses. Linear regression analyses revealed a marginally significant effect of autonomy support on change in percent calories from fat from baseline to 18 months (P=.09), and change in autonomous motivation for diet from baseline to 6 months negatively predicted change in percent calories from fat from baseline to 18 months (β=−0.18, P<.05). Change in perceived competence for dietary change did not predict change in the percent calories from fat (P=.19). There was no predictive effect of autonomy support (P=.18), change in autonomous motivation (P=.29), or change in perceived competence (P=.13) on 18-month change in LDL-C. Thus, only change in autonomous motivation for diet predicted reduction in percent calories from fat | Y56: No | Z56: In person | AA56: 1 | AB56: More than once | AC56: Self-determination theory | AD56: Social support BCT Increase awareness of consequences BCT Goal directed BCT | AE56: 3
A57: Sheridan, S.L., Shadle, J., Simpson, R.J. et al. | B57: The impact of a decision aid about heart disease prevention on patients' discussions with their doctor and their plans for prevention: a pilot randomized trial | C57: 2006 | D57: 10.1186/1472-6963-6-121 | E57: Not effective | F57: Diet, Physical activity, medication changes, smoking cessation | G57: 4 | H57: {=_xlfn.TEXTJOIN(", ", TRUE, IF(OR(ISNUMBER(SEARCH({"blood pressure","heart rate","anthropometrics","ecg","vo2max","spirometry","respiratory rate"},I57))),"Physiological", ""), IF(OR(ISNUMBER(SEARCH({"genetic"},I57))),"Risk", ""), IF(OR(ISNUMBER(SEARCH({"ultrasound","uv photog","facial","oral","CT scan"},I57))),"Imaging", ""), IF(OR(ISNUMBER(SEARCH({"glucose","hb1ac","lipids","nutrient"},I57))),"Blood", ""),IF(OR(ISNUMBER(SEARCH({"anthropometrics"},I57))),"Anthropometry", ""))} -> Physiological, Blood | I57: Blood pressure, blood lipids, ECG | J57: Blood pressure, total and HDL cholesterol, ECG | K57: 3 | M57: Adults (Mean age 53, SD 9) | N57: 75 | O57: 59 | P57: 53 | Q57: No | R57: Yes | S57: 6 months | T57: All patients in the intervention group reviewied the computerized decision aid, Heart to Heart (version 1), which 1) calculates a patient's global risk of CHD events (e.g. angina, myocardial infarction, and death) in the next 10 years by combining information about their age, sex, blood pressure, total and HDL cholesterol, smoking, diabetes, and left ventricular hypertrophy (LVH) status using a continuous Framingham equation; 2) provides patients with individualized information about their global CHD risk, their personal risk factors, the pros and cons of pertinent CHD risk-reducing therapies (e.g. hypertension medication, cholesterol medication, smoking cessation, and aspirin), and the risk reduction achievable after one or more therapeutic interventions; and 3) encourages patients to choose therapies that are acceptable and feasible for long-term CHD risk reduction. The tool encourages a good diet and regular exercise for everyone, but doesn't provide information on how these interventions modify CHD risk. It also provides a summary print-out that can be taken to one's visit with his or her doctor. To assist patients in using Heart to Heart, a research assistant compiled a list of each patient's most recent risk factor information (e.g. most recent blood pressure, most recent total and HDL cholesterol, and electrocardiogram or echo-reported evidence for LVH in the last 3 years) from their medical record and provided it to the patient for use during the decision aid session. Patients then navigated the decision aid at their own speed from computers in the patient education room of our internal medicine clinic. These computers were in a private setting and equipped with a standard keyboard and mouse to facilitate individual input and response. A research assistant was available at all times to answer any questions about decision aid navigation. Patients randomized to the control group received only a list of their CHD risk factors that they could present to their doctor. This list included both qualitative identification of the risk factors and, where appropriate, a quantitative value for the following risk factors: blood pressure, total and HDL cholesterol, smoking, diabetes, and left ventricular hypertrophy (LVH) status. | U57: No | V57: Intention to adopt risk-reduction behaviours (in subsequent 6 months), conversations with healthcare provider, knowledge about effective CHD prevention strategies | W57: No | X57: In unadjusted analysis, 16% (absolute difference; 95% CI -4 to +37%) more patients in the decision aid group talked with their provider about CHD risk reduction and 13% (absolute difference; 95% CI -7% to +34%) more had a specific plan to reduce their CHD risk. When plans were examined more broadly (e.g. including those who independently made a plan, but didn't talk with their doctor), results were similar (absolute difference +16%; 95% CI -1% to 33%). There were too few patients in the study to support adjusted analyses. | Y57: No | Z57: Device/Online | AA57: 1 | AB57: Once | AC57: None | AD57: Increase awareness of consequences BCT | AE57: 1
A58: MARTEAU ET AL | B58: 10.1002/14651858.CD007275.pub2
A59: Marteau, T., Senior, V., Humphries, S.E., Bobrow, M., Cranston, T., Crook, M.A., Day, L., Fernandez, M., Horne, R., Iversen, A., Jackson, Z., Lynas, J., Middleton-Price, H., Savine, R., Sikorski, J., Watson, M., Weinman, J., Wierzbicki, A.S. and Wray, R. | B59: Psychological impact of genetic testing for familial hypercholesterolemia within a previously aware population: A randomized controlled trial | C59: 2004 | D59: 10.1002/ajmg.a.30102 | E59: Not effective | F59: Diet, smoking cessation, medication changes | G59: 3 | H59: {=_xlfn.TEXTJOIN(", ", TRUE, IF(OR(ISNUMBER(SEARCH({"blood pressure","heart rate","anthropometrics","ecg","vo2max","spirometry","respiratory rate"},I59))),"Physiological", ""), IF(OR(ISNUMBER(SEARCH({"genetic"},I59))),"Risk", ""), IF(OR(ISNUMBER(SEARCH({"ultrasound","uv photog","facial","oral","CT scan"},I59))),"Imaging", ""), IF(OR(ISNUMBER(SEARCH({"glucose","hb1ac","lipids","nutrient"},I59))),"Blood", ""),IF(OR(ISNUMBER(SEARCH({"anthropometrics"},I59))),"Anthropometry", ""))} -> Risk | I59: Genetic | J59: Point mutations in the LDLR gene | K59: 1 | L59: RCT | M59: Families, comprising 341 primary participants and 128 adult relatives | N59: 341 | O59: 57 | P59: =(56.2*196+55.9*79+44.1*17+48.9*24)/(196+79+17+24) -> 54.91962 | Q59: No | R59: Yes | S59: 6 months | T59: Participants randomized to one of two groups: (a) routine clinical diagnosis; (b) routine clinical diagnosis plus genetic testing (mutation searching in probands and direct gene testing in relatives). | U59: No | V59: Primary outcomes Perceptions of control were assessed using four internally consistent scales (alphas >0.70) assessing perceived control over (a) FH, (b) cholesterol, (c) heart disease, and (d) fatalism about FH. The five-item perceived control over FH scale and the six-item fatalism about FH scale were taken from the Revised Illness Perceptions Questionnaire. The two-item perceived control over cholesterol and two-item perceived control over heart disease scales were developed in a pilot study specifically for this study. Secondary outcomes Risk-reducing behavior: Standardized measures were used to assess self-reports of smoking, diet, activity level, and cholesterol-lowering medication adherence. Illness and treatment perceptions, Perceptions of the genetic report, and Emotional state were also measured. | W59: No | X59: There were no differences in smoking, diet, exercise, and medication adherence among the three groups, 6 months after the diagnostic assessment. | Y59: No | Z59: In person | AA59: 1 | AB59: Once | AC59: None | AD59: Increase awareness of consequences BCT | AE59: 1
A60: Chao S, Roberts JS, Marteau TM, Silliman R, Cupples LA, Green RC. | B60: Health behavior changes after genetic risk assessment for Alzheimer disease: The REVEAL Study | C60: 2008 | D60: 10.1097/wad.0b013e31815a9dcc | E60: Effective | F60: Diet, Physical activity, medication changes, supplement changes | G60: 4 | H60: {=_xlfn.TEXTJOIN(", ", TRUE, IF(OR(ISNUMBER(SEARCH({"blood pressure","heart rate","anthropometrics","ecg","vo2max","spirometry","respiratory rate"},I60))),"Physiological", ""), IF(OR(ISNUMBER(SEARCH({"genetic"},I60))),"Risk", ""), IF(OR(ISNUMBER(SEARCH({"ultrasound","uv photog","facial","oral","CT scan"},I60))),"Imaging", ""), IF(OR(ISNUMBER(SEARCH({"glucose","hb1ac","lipids","nutrient"},I60))),"Blood", ""),IF(OR(ISNUMBER(SEARCH({"anthropometrics"},I60))),"Anthropometry", ""))} -> Risk | I60: Genetic | J60: ApoE variant | K60: 1 | L60: RCT | M60: Adult children of patients with AD | N60: 162 | O60: 73 | P60: 52.8 | Q60: No | R60: Yes | S60: 12 months | T60: Participants were randomized to either intervention (APOE disclosure) or control (no genotype disclosure) groups. Subjects in both groups received numerical lifetime risk estimates of future AD development based on sex and family history of AD. The intervention group received their APOE genotype. Subjects were informed that no proven preventive measures for AD existed and given an information sheet on preventative therapies under investigation. One year after disclosure, participants were asked 3 questions related to health behavior changes made specifically for the purpose of AD prevention. | U60: No | V60: Changes in diet, changes in PA, or changes in medications and/or vitamins. | W60: Yes | X60: At 12 months, ε4+ participants were significantly more likely than both ε4− participants (52% vs. 24%, P = 0.003) and control participants (52% vs. 30%, P = 0.03) to endorse any AD-specific health behavior change. Of the 3 health behaviors surveyed, ε4+ participants most commonly endorsed changing their medications or vitamins for the purpose of preventing AD. An analysis of open-ended responses to this questionnaire item indicated that adding vitamin E was the most common change in this area. | Y60: No | Z60: Written communication | AA60: 1 | AB60: Once | AC60: None | AD60: Increase awareness of consequences BCT | AE60: 1
A61: HACKAM ET AL | B61: 10.1001/archinternmed.2011.69 | H61: {=_xlfn.TEXTJOIN(", ", TRUE, IF(OR(ISNUMBER(SEARCH({"blood pressure","heart rate","anthropometrics"},I61))),"Monitoring", ""), IF(OR(ISNUMBER(SEARCH({"genetic","ecg","vo2max","spirometry","respiratory rate"},I61))),"Diagnostic", ""), IF(OR(ISNUMBER(SEARCH({"ultrasound","uv photog","facial imaging","oral","CT scan"},I61))),"Imaging", ""), IF(OR(ISNUMBER(SEARCH({"glucose","hb1ac","lipids","nutrient"},I61))),"Blood", ""))}
A62: Bovet P, Perret F, Cornuz J, Quilindo J, Paccaud F. | B62: Improved smoking cessation in smokers given ultrasound photographs of their own atherosclerotic plaques. | C62: 2002 | D62: 10.1006/pmed.2001.0976 | E62: Effective | F62: Smoking cessation | G62: 1 | H62: {=_xlfn.TEXTJOIN(", ", TRUE, IF(OR(ISNUMBER(SEARCH({"blood pressure","heart rate","anthropometrics","ecg","vo2max","spirometry","respiratory rate"},I62))),"Physiological", ""), IF(OR(ISNUMBER(SEARCH({"genetic"},I62))),"Risk", ""), IF(OR(ISNUMBER(SEARCH({"ultrasound","uv photog","facial","oral","CT scan"},I62))),"Imaging", ""), IF(OR(ISNUMBER(SEARCH({"glucose","hb1ac","lipids","nutrient"},I62))),"Blood", ""),IF(OR(ISNUMBER(SEARCH({"anthropometrics"},I62))),"Anthropometry", ""))} -> Imaging | I62: Ultrasound | J62: Ultrasound - carotid and femoral arteries | K62: 1 | M62: Adult smokers | N62: 153 | O62: 16.2 | P62: =(45.7*79+39.2*20+48.9*54)/(79+20+54) -> 45.979739 | Q62: Unclear | R62: No | S62: 6 months | T62: Smokers selected from the general population were randomly allocated to undergo high-resolution B-mode ultrasonography of their carotid and femoral arteries. Thus, participants were divided into 3 groups, smokers not randomized to sonography and not shown a plaque (group A); smokers randomized to ultrasonography with no plaque identified, hence not shown a plaque (group B); and smokers randomized to ultrasonography with at least one plaque, hence shown a plaque (group C). All smokers received quit-smoking counselling. Smokers with > or =1 atherosclerotic plaque were given two photographs of a plaque with a relevant explanation. Quit rates were assessed by telephone 6 months later. | U62: Yes | V62: Smoking cessation | W62: Yes | X62: Seventy-nine smokers did not undergo ultrasonography (A). Among the 74 smokers submitted to ultrasonography, 20 had no plaque (B) and 54 had > or =1 plaque (C). Quit rates were, respectively, 6.3, 5.0, and 22.2% in groups A, B, and C. Quit rates were higher in smokers submitted to ultrasonography (B + C vs A; P = 0.031) and in those receiving photographs (C vs A + B; P = 0.003). Smoking cessation was independently associated with intervention C (OR = 6.2; 95% CI = 1.8-21) and a white-collar job but not with age or gender. | Y62: No | Z62: In person, written communication | AA62: 2 | AB62: Once | AC62: None | AD62: Increase awareness of consequences BCT | AE62: 1
A63: VIRON ET AL. | B63: 10.1371/journal.pone.0040230 | H63: {=_xlfn.TEXTJOIN(", ", TRUE, IF(OR(ISNUMBER(SEARCH({"blood pressure","heart rate","anthropometrics"},I63))),"Monitoring", ""), IF(OR(ISNUMBER(SEARCH({"genetic","ecg","vo2max","spirometry","respiratory rate"},I63))),"Diagnostic", ""), IF(OR(ISNUMBER(SEARCH({"ultrasound","uv photog","facial imaging","oral","CT scan"},I63))),"Imaging", ""), IF(OR(ISNUMBER(SEARCH({"glucose","hb1ac","lipids","nutrient"},I63))),"Blood", ""))}
A64: Ito H, Matsuo K, Wakai K, Saito T, Kumimoto H, et al. | B64: An intervention study of smoking cessation with feedback on genetic cancer susceptibility in Japan | C64: 2006 | D64: 10.1016/j.ypmed.2005.10.006 | E64: Not effective | F64: Smoking cessation | G64: 1 | H64: {=_xlfn.TEXTJOIN(", ", TRUE, IF(OR(ISNUMBER(SEARCH({"blood pressure","heart rate","anthropometrics","ecg","vo2max","spirometry","respiratory rate"},I64))),"Physiological", ""), IF(OR(ISNUMBER(SEARCH({"genetic"},I64))),"Risk", ""), IF(OR(ISNUMBER(SEARCH({"ultrasound","uv photog","facial","oral","CT scan"},I64))),"Imaging", ""), IF(OR(ISNUMBER(SEARCH({"glucose","hb1ac","lipids","nutrient"},I64))),"Blood", ""),IF(OR(ISNUMBER(SEARCH({"anthropometrics"},I64))),"Anthropometry", ""))} -> Risk | I64: Genetic | J64: Genetic - L-myc genotype | K64: 1 | L64: Randomised intervention | M64: Adults smokers, 1st-visit outpatients at Aichi Cancer Center Hospital (about 70% of the outpatients do not have any cancer) | N64: 697 | O64: 40.5 | P64: 46.5 | Q64: No | R64: No | S64: 9 months | T64: Participants were divided into two groups: the biomarker feedback group (BF) and the follow-up smoking status group (FS). The subjects were asked for their smoking status at enrolment and at 3- and 9-month follow-ups. BF subjects were notified about their L-myc genotype. L-myc is a member of the myc gene family, which also includes c-myc and N-myc. The SS genotype of the L-myc EcoRI polymorphism has been reported to be a marker for tumor prognosis with lung and possibly other types of cancers, associated with susceptibility to neoplasia overall. This L-myc polymorphism modifies the effects of smoking on esophageal and lung cancer risk while having no significant influence in itself - Individuals with the LS/SS genotypes were highly susceptible to development of the above cancer types only when they were exposed to cigarette smoking. As part of the consent procedure, a trained interviewer explained the effects of L-myc polymorphism on modulating the cancer risk due to smoking using a flip chart with graphically displayed information for the BF participants. The information they were given was as follows: 1. Those with the risky genotypes have enhanced risk for lung or esophageal cancer if they continue smoking compared with the non-risky genotype; 2. The risk for smokers with risky genotypes can be reduced by stopping smoking; 3. The L-myc polymorphism is not the only modifier of the cancer risk. The FS participants were just followed-up for their smoking status and received no intervention for smoking cessation as well as no information on the L-myc polymorphism. | U64: Yes | V64: Smoking cessation | W64: Yes | X64: For the subjects without cancer for both sexes, the rates of prevalent abstinence were not significantly higher in the BF group (12.7%) than in the FS group (8.4%). The ORs for smoking abstinence at each time point were above unity, indicating increased abstinence in the BF but without statistical significance. For the subjects with cancer, the tendency for abstinence at each time point was opposite to the case for individuals without cancer, albeit without significance. In the sex-stratified analysis, the rates of abstinence among males without cancer at the 9-month follow-up were similar in the two groups (12.3% in the FS and 11.0% in the BF). However, among females without cancer, the rate of abstinence at the 9-month follow-up in the BF was significantly higher (15.0%) than in the FS (5.0% and 4.2%, respectively, OR, 3.59, 95% CI 1.19–10.9). More participants in the BF quit smoking newly at 9-month follow-ups, compared with those among the FS (OR 4.91, 0.92–26.3) for the females without cancer. The trends in all participants were similarly observed, although no impact was evident compared non-cancer subjects. Adjusted ORs for smoking cessation at 9-month follow-up of the FS, and the BF with the information about their genotype, stratified for the L-myc genotype (L-myc LS/SS (risky genotype), n = 167 and LL (non-risky genotype), n = 55): among participants without cancer, the OR for the risky genotypes was significantly increased (OR 2.87, 1.41–5.81) for the BS group compared to the FS group. The abstinence rate for the males with a non-risky genotype was lower than that for the FS, although without significance. None of the non-cancer males with the non-risky genotype quit smoking, while 18.8% of non-cancer males with the risky genotypes did so. For females without cancer, rates of smoking cessation with the risky and the non-risky genotypes were higher than those among the FS group (23.0%, 23.1% and 4.2%, respectively). The ORs were 7.34 (1.64–48.8) and 5.56 (1.64–18.8), respectively, compared with those in the FS. The results among all participants were similar to those among those without cancer. Not effective, however when stratified by sex and cancer status, some effects in females and individuals without cancer. | Y64: No | Z64: In person, written communication | AA64: 2 | AB64: Once | AC64: None | AD64: Increase awareness of consequences BCT | AE64: 1
A65: Hishida, A., Terazawa, T., Mamiya, T., Ito, H., Matsuo, K., Tajima, K., & Hamajima, N. | B65: Efficacy of genotype notification to Japanese smokers on smoking cessation—an intervention study at workplace. | C65: 2010 | D65: 10.1016/j.canep.2009.11.008 | E65: Not effective | F65: Smoking cessation | G65: 1 | H65: {=_xlfn.TEXTJOIN(", ", TRUE, IF(OR(ISNUMBER(SEARCH({"blood pressure","heart rate","anthropometrics","ecg","vo2max","spirometry","respiratory rate"},I65))),"Physiological", ""), IF(OR(ISNUMBER(SEARCH({"genetic"},I65))),"Risk", ""), IF(OR(ISNUMBER(SEARCH({"ultrasound","uv photog","facial","oral","CT scan"},I65))),"Imaging", ""), IF(OR(ISNUMBER(SEARCH({"glucose","hb1ac","lipids","nutrient"},I65))),"Blood", ""),IF(OR(ISNUMBER(SEARCH({"anthropometrics"},I65))),"Anthropometry", ""))} -> Risk | I65: Genetic | J65: Genetic - L-myc genotype | K65: 1 | L65: intervention study | M65: Employees of a bank who smoke. As age is bucketed, mean ages of buckets are used (e.g., "30-39 years" = 34.5 years). Ages above 60 are estimated as 65. | N65: 562 | O65: 6.2 | P65: =(24.5*(54+61)+34.5*(94+90)+44.5*(99+65)+54.5*(35+58)+65*(4+2))/(286+276) -> 39.007117 | Q65: No | R65: No | S65: 12 months | T65: The effects of genotype notification of an oncogene (L-myc) genotype to smokers on their behavior to quit smoking. Subjects were employees of a bank, who answered to be a smoker for a qestionnaire used at annual health checkup at workplace from July to December in 2002. Informed consent of genotype notification was obtained individually from each smoker after handing the participants a booklet named “Smoking and genetic polymorphism: what is the genetic traits to cause tobacco-related diseases. Hi smokers! Can your genes bear tobacco?”. The booklet was made of eight colored pages including information on tobacco-related diseases, genetic polymorphisms in general, concept of tobacco carcinogen susceptible genotypes, CYP1A1, GSTM1, L-myc, relative risk of L-Myc genotype for esophageal cancer, genotypes associated with nicotine dependence, damages caused by smoking, and benefits of smoking cessation. The information given about the L-myc genotype in this booklet is as follows: "L-myc gene has a missense G/T polymorphism at nucleotide position 2886, G/G, G/T and T/T genotype of which is called LL, LS and SS genotype, respectively. Our case–control study at Aichi Cancer Center revealed that the OR of esophageal cancer for smoking was 7.57 in SS, 6.40 in LS and 1.77 in LL, respectively". In three months (August, October and December in 2002), 257 participants (89.9%) among 286 smokers invited (“intervention group”) agreed to genotype testing. Blood samples were numbered in a manner corresponding to the questionnaire, but the name of participants was not attached to the tubes of the blood sample. The health staff recorded the number for each participant. In the other three months (July, September and November in 2002), all 276 smokers agreed to be followed up as a control group. Three months after the enrollment, genotype reports were sent in sealed envelopes to the section of health management. In the reports, the explanation was attached that smoking elevates the risk of esophageal cancer substantially among those with SS (OR = 8) and LS (OR = 7), while OR = 2 among those with LL genotype, and similar for lung cancer. Additionally, the explanation that there are many genotypes associated with the susceptibility of smoking was provided. The staff (public nurses) handed the report to each participant without opening the envelope according to the number specified on the envelope. They added general comments on the genotype for each participant, and provide specific comments when participants asked the details. Strong messages to quit smoking were not included their explanation. | U65: No | V65: One year after the enrollment, a follow-up questionnaire about the stage of change was conducted for all participants. | W65: No | X65: Those who stated to have quitted smoking were 22 (8.0%) among the 276 controls and 15 (5.8%) among the 257 genotype notified participants. The difference in the cessation rate between the two groups was not significant (p = 0.395). When 29 smokers who refused genotype tests were regarded as non-quitters, the cessation rate of whole intervention group was 5.2% (p = 0.234 in comparison with the rate among the controls). The OR of cessation for the intervention adjusted by age, sex and stage at enrollment was not statistically significant (OR = 0.64, 95% CI 0.32–1.28, p = 0.209). Among non-quitters, the difference in the stage of smokers at one year after enrollment between the two groups was not significant (χ2 = 0.961 d.f. = 3, p = 0.811). In both groups, the subjects in the stage of “wish to quit” (11.8% in the intervention group and 11.1% in the controls) tended to have a high cessation rate compared with “no concern” (0.0% and 4.3%, respectively) or “no intention” (6.2% and 8.2%) group, although statistically not significant. Cessation rates did not differ significantly according to L-myc genotype (5.6% in LS and 7.1% in SS, compared with 4.9% in LL; p = 1.000 and p = 0.723, respectively). As for the responses to genotype notification, those who felt “anxious” after notification showed an insignificantly higher cessation rate than those who felt “relieved” after notification (6.7% in “anxious” and 3.6% in “relieved”; p = 1.000). Those who stated “relieved” was 41.0% in LL, 2.4% in LS, and 0.0% in SS; the percentage for LL was significantly higher than that for LS or SS (p < 0.001 and p < 0.001, respectively). Those who stated “anxious” was 11.5% in LL, 31.0% in LS, and 41.4% in SS; the percentage for LS or SS was significantly higher than that for LL (p = 0.004 and p < 0.001, respectively). There were no claims or consultations on genotype to the health management section, and serious responses of the genotype-notified participants were not observed throughout the study. | Y65: No | Z65: Written communication | AA65: 1 | AB65: Once | AC65: None | AD65: Increase awareness of consequences BCT | AE65: 1
A66: McBride, C. M., Bepler, G., Lipkus, I. M., Lyna, P., Samsa, G., Albright, J., ... & Rimer, B. K. (2002) | B66: Incorporating genetic susceptibility feedback into a smoking cessation program for African-American smokers with low income. | C66: 2002 | D66: https://aacrjournals.org/cebp/article/11/6/521/166621/Incorporating-Genetic-Susceptibility-Feedback-into | E66: Not effective | F66: Smoking cessation | G66: 1 | H66: {=_xlfn.TEXTJOIN(", ", TRUE, IF(OR(ISNUMBER(SEARCH({"blood pressure","heart rate","anthropometrics","ecg","vo2max","spirometry","respiratory rate"},I66))),"Physiological", ""), IF(OR(ISNUMBER(SEARCH({"genetic"},I66))),"Risk", ""), IF(OR(ISNUMBER(SEARCH({"ultrasound","uv photog","facial","oral","CT scan"},I66))),"Imaging", ""), IF(OR(ISNUMBER(SEARCH({"glucose","hb1ac","lipids","nutrient"},I66))),"Blood", ""),IF(OR(ISNUMBER(SEARCH({"anthropometrics"},I66))),"Anthropometry", ""))} -> Risk | I66: Genetic | J66: Genetic - GST3 | K66: 1 | L66: RCT | M66: Current smokers | N66: 557 | O66: 60 | P66: 44 | Q66: No | R66: No | S66: 12 months | T66: Eligible smokers randomised in a 1:2 ratio to Enhanced Usual Care or Biomarker Feedback (BF). Surveys were conducted at baseline, 6, and 12 months later. All smokers received a self-help manual and, if appropriate, nicotine patches. Smokers in the BF arm also were offered a blood test for genotyping the GST3 gene (GSTM1), sent a test result booklet, and called up to four times by a health educator. | U66: Yes | V66: Prevalent abstinence was assessed by self-report of having smoked no cigarettes in the prior 7 days at the 6- and 12-month follow-ups and sustained abstinence, i.e., not smoking at either follow-up or in-between | W66: Yes | X66: Efforts to biochemically confirm self-reported cessation were unsuccessful. Only 39% (24 of 61) of those who reported abstinence and agreed to provide a saliva sample returned one. Rates of return did not differ between the two arms (P = 0.78). Thus, trial outcomes are based on self-reported cessation. Smoking cessation was greater for the BF arm than the Enhanced Usual Care arm (19% versus 10%, respectively; P < 0.006) at 6 months but not at 12 months. Cessation rates among those with heightened susceptibility to lung cancer (GSTM1 missing, n = 104) were compared with those with results that indicated they were not “susceptible” (GSTM1 present, n = 204). Rates of prevalent and sustained abstinence for those with the enzyme missing or present did not differ significantly at follow-up: 6 months, 17 and 23%, respectively; 12 months, 18 and 15%; sustained, 12 and 12%. Among those who declined the test, rates of prevalent abstinence at 6 and 12 months and sustained abstinence were substantially lower (11, 11, and 5% for each outcome and time point, respectively). | Y66: No | Z66: Telephone, written communication | AA66: 2 | AB66: More than once | AC66: None | AD66: Advise specific behaviour BCT Guide how to perform behaviour BCT Increase awareness of consequences BCT Social support BCT Monitoring Promote pharmacological support BCT' | AE66: 6
A67: BIZE ET AL. | B67: 10.1002/14651858.CD004705.pub4
A68: Parkes G, Greenhalgh T, Griffin M, Dent R. | B68: Effect on smoking quit rate of telling patients their lung age: the Step2quit randomised controlled trial | C68: 2008 | D68: 10.1136/bmj.39503.582396.25 | E68: Effective | F68: Smoking cessation | G68: 1 | H68: {=_xlfn.TEXTJOIN(", ", TRUE, IF(OR(ISNUMBER(SEARCH({"blood pressure","heart rate","anthropometrics","ecg","vo2max","spirometry","respiratory rate"},I68))),"Physiological", ""), IF(OR(ISNUMBER(SEARCH({"genetic"},I68))),"Risk", ""), IF(OR(ISNUMBER(SEARCH({"ultrasound","uv photog","facial","oral","CT scan"},I68))),"Imaging", ""), IF(OR(ISNUMBER(SEARCH({"glucose","hb1ac","lipids","nutrient"},I68))),"Blood", ""),IF(OR(ISNUMBER(SEARCH({"anthropometrics"},I68))),"Anthropometry", ""))} -> Physiological | I68: Spirometry | J68: Spirometry, cotinine testing | K68: 1 | L68: RCT | M68: Current smokers aged over 35 (recruited from GP clinics, no disease) | N68: 561 | O68: 54 | P68: 53 | Q68: No | R68: No | S68: 12 months | T68: All participants underwent standard measurements of lung function (FEV1, FVC (forced vital capacity), FEV1/FVC) with a Micromedical spirometer. Reversibility of airways obstruction was measured according to standard British Thoracic Society guidelines (over 15% and at least 400 ml improvement in FEV1 after 400 µg salbutamol via a spacer). Both groups were told that their lung function would be measured again after 12 months to see whether it had deteriorated. They were not randomised until after spirometry had been completed. All participants were strongly encouraged to give up smoking and advised how to access local NHS smoking cessation clinics. Participants in the intervention group were given their results verbally, immediately after randomisation, in the form of “lung age” with a graphic display. Graphs were used as a visual aid to explain how the lung function normally reduces gradually with age and that smoking can damage lungs as if they are ageing more rapidly than normal. Furthermore they were told that smoking cessation would slow down the rate of deterioration of the lung function back to normal but would not repair the damage already done. In the intervention group, if the lung age was equal to or less than the individual’s chronological age, he or she was informed that test result was normal. If lung age was greater than chronological age, we gave them the “lung age” in years. We did not tell those in the control group their results but informed them that they would be invited for a second test after 12 months to “see if there had been any change in lung function.” If the examiner was pressed for more information, he or she could tell participants that they would receive a letter with more information from the research doctor within four weeks. The letter to both groups included the phrase “This type of lung function test does not tell us anything about the risk of other serious diseases related to smoking such as lung cancer or heart disease or stroke. Smoking cessation is therefore still important for all people regardless of their age or the results of these lung tests.” All participants were given written contact details of the local NHS smoking cessation services. In both groups, when reversibility testing indicated asthma (over 15% and at least 400 ml improvement in FEV1 after 400 µg salbutamol via a spacer) we advised participants to attend their general practitioner for further management, and informed the general practitioner separately. When spirometry findings suggested restrictive lung disease, we sent the participant and his or her general practitioner a letter to alert them to the advisability of further investigation and guidelines on referral to secondary care. | U68: No | V68: The primary outcome measure was verified cessation of smoking 12 months after the initial recruitment interview and examination. Secondary outcomes were changes in daily consumption of cigarettes and the identification of new diagnoses. Participants underwent follow-up examination with repeat spirometry after 12 months. Self reported quitters had carbon monoxide breath testing immediately for confirmation of smoking cessation, and they were informed that they would be contacted by an independent nurse for a saliva test for cotinine measurement. | W68: Yes | X68: Despite an average of 33 pack years of smoking, most participants in this study had “normal” results on spirometry at baseline. 23.5% of the control group and 26.8% of the intervention group had baseline lung function in the “abnormal” range. Those who did not return for follow-up (32 and 31, respectively, in the control and intervention group) were analysed as if they continued to smoke. Verified quit rates were 6.4% (18/281) in the control group and 13.6% (38/280) in the intervention group (difference 7.2%, P=0.005, 95% confidence interval 2.2% to 12.1%). Telling participants their lung age was thus associated with an absolute reduction of 7.2% in the smoking rate compared with giving them their lung function tests results as raw FEV1 data. The number needed to treat (NNT) for the intervention to achieve one additional sustained quitter is 14. Both groups reduced their average self reported consumption of cigarettes; average consumption at follow-up was significantly lower in the intervention group than in the control group (11.7 (SD 9.7) v 13.7 (SD 10.5) per day, P=0.03). The numbers of smokers in both groups who used additional help to quit (health service clinics, nicotine replacement, bupropion, acupuncture, hypnosis) were 22 (7.8%) in the control group and 30 (10.7%) in the intervention group (P=0.2). | Y68: No | Z68: Written communication | AA68: 1 | AB68: Once | AC68: None | AD68: Increase awareness of consequences BCT Advise specific behaviour BCT | AE68: 2
A69: van der Aalst CM, van den Bergh KA, Willemsen MC, de Koning HJ, van Klaveren RJ. | B69: Lung cancer screening and smoking abstinence: 2 year follow-up data from the Dutch-Belgian randomised controlled lung cancer screening trial. | C69: 2010 | D69: 10.1136/thx.2009.133751 | E69: Not effective | F69: Smoking Cessation | G69: 1 | H69: {=_xlfn.TEXTJOIN(", ", TRUE, IF(OR(ISNUMBER(SEARCH({"blood pressure","heart rate","anthropometrics","ecg","vo2max","spirometry","respiratory rate"},I69))),"Physiological", ""), IF(OR(ISNUMBER(SEARCH({"genetic"},I69))),"Risk", ""), IF(OR(ISNUMBER(SEARCH({"ultrasound","uv photog","facial","oral","CT scan"},I69))),"Imaging", ""), IF(OR(ISNUMBER(SEARCH({"glucose","hb1ac","lipids","nutrient"},I69))),"Blood", ""),IF(OR(ISNUMBER(SEARCH({"anthropometrics"},I69))),"Anthropometry", ""))} -> Imaging | I69: CT scan | J69: Lung cancer screening (CT scan) | K69: 1 | L69: RCT | M69: Men who were current or former smokers who had smoked >15 cigarettes a day for >25 yrs or >10 cigarettes a day for >30 yrs. Former smokers should have quit smoking for ≤10 yrs, aged 50-75 years. | N69: 1284 | O69: 0 | P69: 58 | Q69: No | R69: Yes | S69: 4 years | T69: Smoking behaviour was evaluated in two random samples of male smokers in the screen (n=641) and control arm(n=643) before (T0) and 2 years after randomisation (T1). Participants were randomised (1:1) to the screen or control arm. Screen arm participants received CT screening for lung cancer in years 1, 2, and 4, whereas participants in the control arm received no screening (usual care). A fourth scan round was recently started 5.5 years after the baseline screening (year 6.5). The CT screening test results used a novel nodule management strategy based on volume and volume doubling time (VDT). The test results could be either negative, indeterminate or positive. An indeterminate or negative screening result was communicated via a standard letter with an explanation in cases where the radiologists had found an abnormality. Those with an indeterminate test result were informed about the follow-up scan. Participants with a positive screening result were informed about their referral to a pulmonologist for a work-up and diagnosis by phone. At randomisation, all current smokers received a standard brochure or tailoring assessment for tailored smoking cessation information (1:1). The tailoring questionnaire had to be completed and sent back before participants could receive the computer-tailored smoking cessation information (CTSCI). After two and four years of follow-up, subsamples in the screen and control arm received a smoking cessation questionnaire. | U69: No | V69: Intention to quit smoking, Time to first cigarette after waking | W69: No | X69: No difference in number of attempts to quit after 2 years, between screening or control arms. Control arm had higher point prevalence of smoking abstinence (OR = 1.38, 95%CI: 1.01-1.90) and higher prolonged (OR = 1.40; 95% CI: 1.01-1.92) and continued abstinence rates (OR = 1.42, 95% CI: 1.03-1.96), compared to the screening arm. | Y69: No | Z69: Written Communication | AA69: 1 | AB69: Once | AC69: Transtheoretical model (stages of change) | AD69: Increase awareness of consequences BCT Guide how to perform behaviour BCT | AE69: 2
